Workbook

Sheet Ringkasan PRISMA
A1: Ringkasan angka PRISMA 2020
A2: Kolom hasil hitung dihitung dari lembar kerja. Selisih nol berarti angka sudah sama dengan diagram.
A4: Tahap | B4: Keterangan | C4: Menurut diagram PRISMA | D4: Hasil hitung lembar kerja | E4: Selisih
A5: Identifikasi | B5: Rekaman dari PubMed | C5: 1463 | D5: =COUNTIF('Ekspor gabungan'!$C$5:$C$4743,"PubMed") -> 1463 | E5: =D5-C5 -> 0
A6: Identifikasi | B6: Rekaman dari Scopus | C6: 1148 | D6: =COUNTIF('Ekspor gabungan'!$C$5:$C$4743,"Scopus") -> 1148 | E6: =D6-C6 -> 0
A7: Identifikasi | B7: Rekaman dari Cochrane Library | C7: 231 | D7: =COUNTIF('Ekspor gabungan'!$C$5:$C$4743,"Cochrane Library") -> 231 | E7: =D7-C7 -> 0
A8: Identifikasi | B8: Rekaman dari EBSCOhost | C8: 659 | D8: =COUNTIF('Ekspor gabungan'!$C$5:$C$4743,"EBSCOhost") -> 659 | E8: =D8-C8 -> 0
A9: Identifikasi | B9: Rekaman dari ProQuest | C9: 86 | D9: =COUNTIF('Ekspor gabungan'!$C$5:$C$4743,"ProQuest") -> 86 | E9: =D9-C9 -> 0
A10: Identifikasi | B10: Rekaman dari Europe PMC | C10: 903 | D10: =COUNTIF('Ekspor gabungan'!$C$5:$C$4743,"Europe PMC") -> 903 | E10: =D10-C10 -> 0
A11: Identifikasi | B11: Rekaman dari medRxiv | C11: 249 | D11: =COUNTIF('Ekspor gabungan'!$C$5:$C$4743,"medRxiv") -> 249 | E11: =D11-C11 -> 0
A12: Identifikasi | B12: Total rekaman dari tujuh basis data | C12: 4739 | D12: =COUNTA('Ekspor gabungan'!$B$5:$B$4743) -> 4739 | E12: =D12-C12 -> 0
A13: Identifikasi | B13: Duplikat dihapus | C13: 2262 | D13: =COUNTIF('Ekspor gabungan'!$J$5:$J$4743,"Duplikat") -> 2262 | E13: =D13-C13 -> 0
A14: Skrining | B14: Rekaman diskrining | C14: 2477 | D14: =COUNTA('Skrining judul abstrak'!$A$5:$A$2481) -> 2477 | E14: =D14-C14 -> 0
A15: Skrining | B15: Rekaman dieksklusi pada judul dan abstrak | C15: 2368 | D15: =COUNTIF('Skrining judul abstrak'!$M$5:$M$2481,"Dieksklusi") -> 2368 | E15: =D15-C15 -> 0
A16: Skrining | B16: Laporan dicari naskah lengkapnya | C16: 109 | D16: =COUNTIF('Skrining judul abstrak'!$M$5:$M$2481,"Lanjut ke teks lengkap") -> 109 | E16: =D16-C16 -> 0
A17: Skrining | B17: Laporan tidak berhasil diperoleh | C17: 3 | D17: =COUNTIF('Teks lengkap'!$H$5:$H$113,"Tidak diperoleh") -> 3 | E17: =D17-C17 -> 0
A18: Kelayakan | B18: Laporan dinilai kelayakannya | C18: 106 | D18: =COUNTIF('Teks lengkap'!$G$5:$G$113,"Diperoleh") -> 106 | E18: =D18-C18 -> 0
A19: Kelayakan | B19: Dieksklusi, bukan populasi edema paru kardiogenik akut | C19: 46 | D19: =COUNTIF('Teks lengkap'!$I$5:$I$113,"Bukan populasi edema paru kardiogenik akut") -> 46 | E19: =D19-C19 -> 0
A20: Kelayakan | B20: Dieksklusi, bukan perbandingan NIV dengan oksigenasi konvensional | C20: 16 | D20: =COUNTIF('Teks lengkap'!$I$5:$I$113,"Bukan perbandingan NIV dengan oksigenasi konvensional") -> 16 | E20: =D20-C20 -> 0
A21: Kelayakan | B21: Dieksklusi, mortalitas rumah sakit tidak dilaporkan | C21: 30 | D21: =COUNTIF('Teks lengkap'!$I$5:$I$113,"Mortalitas rumah sakit tidak dilaporkan") -> 30 | E21: =D21-C21 -> 0
A22: Kelayakan | B22: Dieksklusi, laporan ganda atau telah digantikan versi terbaru | C22: 6 | D22: =COUNTIF('Teks lengkap'!$I$5:$I$113,"Laporan ganda atau telah digantikan versi terbaru") -> 6 | E22: =D22-C22 -> 0
A23: Kelayakan | B23: Total dieksklusi pada teks lengkap | C23: 98 | D23: =COUNTIF('Teks lengkap'!$H$5:$H$113,"Dieksklusi") -> 98 | E23: =D23-C23 -> 0
A24: Disertakan | B24: Studi disertakan dari basis data | C24: 8 | D24: =COUNTIF('Teks lengkap'!$H$5:$H$113,"Disertakan") -> 8 | E24: =D24-C24 -> 0
A25: Penelusuran manual | B25: Rekaman dari Jurnal Kardiologi Indonesia (JKI) | C25: 8 | D25: =COUNTIF('Manual searching'!$B$5:$B$58,"Jurnal Kardiologi Indonesia (JKI)") -> 8 | E25: =D25-C25 -> 0
A26: Penelusuran manual | B26: Rekaman dari Jurnal Respirologi Indonesia (JRI) | C26: 2 | D26: =COUNTIF('Manual searching'!$B$5:$B$58,"Jurnal Respirologi Indonesia (JRI)") -> 2 | E26: =D26-C26 -> 0
A27: Penelusuran manual | B27: Rekaman dari JAI (Jurnal Anestesiologi Indonesia) | C27: 6 | D27: =COUNTIF('Manual searching'!$B$5:$B$58,"JAI (Jurnal Anestesiologi Indonesia)") -> 6 | E27: =D27-C27 -> 0
A28: Penelusuran manual | B28: Rekaman dari Majalah Anestesia dan Critical Care (MACC) | C28: 5 | D28: =COUNTIF('Manual searching'!$B$5:$B$58,"Majalah Anestesia dan Critical Care (MACC)") -> 5 | E28: =D28-C28 -> 0
A29: Penelusuran manual | B29: Rekaman dari Solo Journal of Anesthesi, Pain and Critical Care (SOJA) | C29: 1 | D29: =COUNTIF('Manual searching'!$B$5:$B$58,"Solo Journal of Anesthesi, Pain and Critical Care (SOJA)") -> 1 | E29: =D29-C29 -> 0
A30: Penelusuran manual | B30: Rekaman dari Current Internal Medicine Research and Practice Surabaya Journal (CIMRJ) | C30: 1 | D30: =COUNTIF('Manual searching'!$B$5:$B$58,"Current Internal Medicine Research and Practice Surabaya Journal (CIMRJ)") -> 1 | E30: =D30-C30 -> 0
A31: Penelusuran manual | B31: Rekaman dari Cardiovascular and Cardiometabolic Journal (CCJ) | C31: 2 | D31: =COUNTIF('Manual searching'!$B$5:$B$58,"Cardiovascular and Cardiometabolic Journal (CCJ)") -> 2 | E31: =D31-C31 -> 0
A32: Penelusuran manual | B32: Rekaman dari Majalah Kedokteran Indonesia (JIMA) | C32: 1 | D32: =COUNTIF('Manual searching'!$B$5:$B$58,"Majalah Kedokteran Indonesia (JIMA)") -> 1 | E32: =D32-C32 -> 0
A33: Penelusuran manual | B33: Rekaman dari eJournal Kedokteran Indonesia (eJKI) | C33: 0 | D33: =COUNTIF('Manual searching'!$B$5:$B$58,"eJournal Kedokteran Indonesia (eJKI)") -> 0 | E33: =D33-C33 -> 0
A34: Penelusuran manual | B34: Rekaman dari Indonesian Journal of Chest (IJC) | C34: 1 | D34: =COUNTIF('Manual searching'!$B$5:$B$58,"Indonesian Journal of Chest (IJC)") -> 1 | E34: =D34-C34 -> 0
A35: Penelusuran manual | B35: Rekaman dari Jurnal Gawat Darurat (JGD) | C35: 0 | D35: =COUNTIF('Manual searching'!$B$5:$B$58,"Jurnal Gawat Darurat (JGD)") -> 0 | E35: =D35-C35 -> 0
A36: Penelusuran manual | B36: Rekaman dari Jurnal Penyakit Dalam Indonesia (JPDI) | C36: 27 | D36: =COUNTIF('Manual searching'!$B$5:$B$58,"Jurnal Penyakit Dalam Indonesia (JPDI)") -> 27 | E36: =D36-C36 -> 0
A37: Penelusuran manual | B37: Total rekaman penelusuran manual | C37: 54 | D37: =COUNTA('Manual searching'!$A$5:$A$58) -> 54 | E37: =D37-C37 -> 0
A38: Penelusuran manual | B38: Laporan dicari | C38: 54 | D38: =COUNTIF('Manual searching'!$J$5:$J$58,"Ya") -> 54 | E38: =D38-C38 -> 0
A39: Penelusuran manual | B39: Laporan dinilai kelayakannya | C39: 54 | D39: =COUNTIF('Manual searching'!$K$5:$K$58,"Ya") -> 54 | E39: =D39-C39 -> 0
A40: Penelusuran manual | B40: Dieksklusi, bukan populasi edema paru kardiogenik akut | C40: 29 | D40: =COUNTIF('Manual searching'!$M$5:$M$58,"Bukan populasi edema paru kardiogenik akut") -> 29 | E40: =D40-C40 -> 0
A41: Penelusuran manual | B41: Dieksklusi, tidak memuat intervensi NIV, CPAP, maupun BiPAP | C41: 25 | D41: =COUNTIF('Manual searching'!$M$5:$M$58,"Tidak memuat intervensi NIV, CPAP, maupun BiPAP") -> 25 | E41: =D41-C41 -> 0
A42: Penelusuran manual | B42: Studi disertakan dari penelusuran manual | C42: 0 | D42: =COUNTIF('Manual searching'!$L$5:$L$58,"Disertakan") -> 0 | E42: =D42-C42 -> 0
A43: Total akhir | B43: Studi disertakan dalam telaah | C43: 8 | D43: =D24+D42 -> 8 | E43: =D43-C43 -> 0

Sheet Ekspor gabungan
A1: Ekspor gabungan dari tujuh basis data (n = 4.739)
A2: Pencarian 24 Oktober 2026 pukul 21.00 WIB. Rekaman yang sudah muncul pada basis data sebelumnya ditandai Duplikat.
A4: No | B4: ID rekaman | C4: Basis data | D4: DOI | E4: Penulis | F4: Judul | G4: Tahun | H4: Jurnal | I4: Abstrak | J4: Status | K4: Verifikasi Crossref
A5: 1 | B5: S0052 | C5: PubMed | D5: 10.1016/s1388-9842(99)00008-2 | E5: Richardson M, Cockburn N, Cleland JGF | F5: Update of Recent Clinical Trials in Heart Failure and Myocardial Infarction | G5: 1999 | H5: European Journal of Heart Failure | I5: There are currently many on-going clinical trials assessing therapies for the treatment of patients with heart failure. The purpose of this series of papers is to present concise summaries of current randomised trials in the field of heart failure and myocardial infarction (MI). Data from large double-blind, placebo-controlled trials, which are on-going or have only recently been published, are given in a format allowing easy comparison. Where appropriate, data from smaller studies are included. Major studies which are examined in this issue include CIBIS II, MERIT-HF, RESOLVD, SPICE, VEST, MACH-1, ATLAS, RALES, CIDS and CASH. These trials assess the efficacy and safety of beta-blocker, angiotensin-II-receptor blocker, positive inotropic agent, calcium antagonist, angiotensin-converting enzyme (ACE) inhibitor, aldosterone receptor blocker, and antiarrhythmic interventions in the treatment of heart failure. The presentation of data from these on-going trials should allow an up-to-date assessment, by physicians, of the most appropriate and effective treatment for patients with heart failure. It is evident that some therapies may play no further role in the treatment of heart failure, due to the increased risk of mortality associated with their administration, whilst others may convey significant benefits. | J5: Asli | K5: Terverifikasi
A6: 2 | B6: S0610 | C6: PubMed | D6: 10.1164/ajrccm.153.3.8630538 | E6: Patrick W, Webster K, Ludwig L, Roberts D, Wiebe P, Younes M | F6: Noninvasive Positive-Pressure Ventilation in Acute Respiratory Distress Without Prior Chronic Respiratory Failure | G6: 1996 | H6: American journal of respiratory and critical care medicine | I6: We evaluated the efficacy of noninvasive mechanical ventilation (NIMV) in alleviating distress and avoiding intubation in patients with de novo acute respiratory failure complicating primary medical disorders. Eleven consecutive patients with severe respiratory distress were entered. In all patients a decision to intubate on an urgent basis had been made, but NIMV could be initiated within minutes. The patients suffered from acute pulmonary edema (five), sepsis/ARDS (two), status asthmaticus (two), and severe pneumonia (two). Dyspnea score (max=10) was (+/- SD) 8.4 +.- 1.6, scale for accessory muscle use (max=5) was 4.2 +/- 0.7, and respiratory rate was 37.6 +/- 3.8 min -1. Pa CO2, pH, and base excess (BE) were 48 +/- 18 mm Hg, 7.27 +/- 0.13, and -5.5 +/- 7.4, respectively, with five patients showing severe metabolic acidosis (BE &amp;lt; - 10). NIMV was applied using proportional assist ventilation. There were three early failures. These included the two patients with sepsis/ARDS who did not tolerate the mask. One patient failed because Pa CO2 and pH deteriorated despite subjective improvement. The remaining eight patients demonstrated progressive improvement, and none required intubation. The duration of NIMV was 3 h to 2 d. We conclude that when NIMV is made available on a "few minutes" basis, selected patients with severe de novo respiratory distress/failure caused by reversible medical disorders, who would otherwise have been intubated, can be given substantial relief and be spared intubation. | J6: Asli | K6: Terverifikasi
A7: 3 | B7: S1484 | C7: PubMed | D7: 10.1016/s1388-9842(00)00058-1 | E7: Kiilavuori K, Näveri H, Salmi T, Härkönen M | F7: The Effect of Physical Training on Skeletal Muscle in Patients with Chronic Heart Failure | G7: 2000 | H7: European Journal of Heart Failure | I7: The improvement of exercise capacity in patients with chronic heart failure (CHF) by physical training has been connected with reversal of the abnormalities in muscle fiber distribution and with the reduced activity of the enzymes of oxidative metabolism in skeletal muscle. However, the change in fiber type distribution induced by training is controversial and in previous studies the activities of the rate-limiting enzymes of the metabolic pathways have not been measured. To examine the effect of dynamic training on percentage distribution of muscle fibers, on activities of the rate-limiting enzymes of the metabolic pathways and on electrophysiology in skeletal muscle. A total of 27 patients with stable CHF (NYHA class II–III) were randomized to a training (N=12) or a control (N=15) group. The training group exercised on a bicycle ergometer for 30 min three times a week for 3 months using a load corresponding to 50–60% of their peak oxygen consumption. This was followed by a 3-month training period at home according to personal instructions. The control group did not change its physical activities. We studied muscle histology and measured the activities of the rate-limiting enzymes of anaerobic glycolysis (phosphofructokinase, PFK), glycogenolysis (phosphorylase), citric acid cycle (α-ketoglurate dehydrogenase, KGDH) and fatty acid oxidation (carnitinepalmitoyl transferase I and II, CPT I and II) from biopsies of the vastus lateralis muscle at baseline and after 3 and 6 months. Muscle strength and strength endurance with surface EMG and macro EMG of the right knee extensors were also determined. Exercise capacity, particularly submaximal, improved in the training group. The activity of PFK rose significantly but that of the other enzymes did not when compared with the change in the controls. Training had no effect on the percentage distribution of slow-twitch and fast-twitch muscle fibers or on capillary density around these fibers in skeletal muscle. Maximum voluntary force, strength endurance and the function of motor units remained unaffected. Dynamic training results in improved exercise endurance in CHF. In skeletal muscle, the capacity of anaerobic glycolysis is increased but that of the citric acid cycle and fatty acid oxidation is not. Furthermore, the improvement in exercise endurance seems to be independent of changes in the percentage distribution of muscle fibers, capillarity or electrophysiological factors. | J7: Asli | K7: Terverifikasi
A8: 4 | B8: S1264 | C8: PubMed | D8: 10.1136/heart.87.3.229 | E8: Struthers AD, Donnan PT, Lindsay P, McNaughton D, Broomhall J, MacDonald TM | F8: Effect of allopurinol on mortality and hospitalisations in chronic heart failure: a retrospective cohort study | G8: 2002 | H8: Heart | I8: Objective: To examine whether allopurinol is associated with any alteration in mortality and hospitalisations in patients with chronic heart failure (CHF). This hypothesis is based on previous data that a high urate concentration is independently associated with mortality with a risk ratio of 4.23 in CHF. Design: Retrospective cohort study. Setting: Medicines Monitoring Unit, Ninewells Hospital, Dundee, UK. Patients: 1760 CHF patients divided into four groups: those on no allopurinol, those on long term low dose allopurinol, those on short term low dose allopurinol, and those on long term high dose allopurinol. Main outcome measures: Total mortality, cardiovascular mortality, cardiovascular hospitalisations, cardiovascular mortality or hospitalisations. Results: Long term low dose allopurinol was associated with a significant worsening in mortality over those who never received allopurinol (relative risk 2.04, 95% confidence interval (CI) 1.48 to 2.81). This may be because low dose allopurinol is insufficient to negate the adverse effect of a high urate concentration. However, long term high dose (≥ 300 mg/day) allopurinol was associated with a significantly better mortality than longstanding low dose allopurinol (relative risk 0.59, 95% CI 0.37 to 0.95). This may mean that high dose allopurinol can fully negate the adverse effect of urate and return the mortality to normal. Conclusions: Long term high dose allopurinol may be associated with a better mortality than long term low dose allopurinol in patients with CHF because of a dose related beneficial effect of allopurinol against the well described adverse effect of urate. Further work is required to substantiate or refute this finding. | J8: Asli | K8: Terverifikasi
A9: 5 | B9: S1896 | C9: PubMed | D9: 10.1310/hpj4804-270 | E9: Mancano MA | F9: Statin-Induced Lung Injury; Colchicine-Induced Rhabdomyolysis Caused by Interaction with Clarithromycin; Disulfiram Ethanol Reaction Mimicking Anaphylactic, Cardiogenic, and Septic Shock; Weight Gain with Abdominal Enlargement in a Patient Receiving Tocilizumab; Nilotinib-Associated Acute Pancreatitis | G9: 2013 | H9: Hospital Pharmacy | I9: The purpose of this feature is to heighten awareness of specific adverse drug reactions (ADRs), discuss methods of prevention, and promote reporting of ADRs to the US Food and Drug Administration's (FDA's) MedWatch program (800-FDA-1088). If you have reported an interesting, preventable ADR to MedWatch, please consider sharing the account with our readers. | J9: Asli | K9: Terverifikasi
A10: 6 | B10: S2347 | C10: PubMed | D10: 10.1002/14651858.cd005351.pub3 | E10: Vital FM, Ladeira MT, Atallah ÁN | F10: Non-invasive positive pressure ventilation (CPAP or bilevel NPPV) for cardiogenic pulmonary oedema | G10: 2013 | H10: Cochrane Database of Systematic Reviews | I10: This is an update of a systematic review previously published in 2008 about non-invasive positive pressure ventilation (NPPV). NPPV has been widely used to alleviate signs and symptoms of respiratory distress due to cardiogenic pulmonary oedema. NPPV prevents alveolar collapse and helps redistribute intra-alveolar fluid, improving pulmonary compliance and reducing the pressure of breathing. To determine the effectiveness and safety of NPPV in the treatment of adult patients with cardiogenic pulmonary oedema in its acute stage. We searched the following databases on 20 April 2011: CENTRAL and DARE, (The Cochrane Library, Issue 2 of 4, 2011); MEDLINE (Ovid, 1950 to April 2011); EMBASE (Ovid, 1980 to April 2011); CINAHL (1982 to April 2011); and LILACS (1982 to April 2011). We also reviewed reference lists of included studies and contacted experts and equipment manufacturers. We did not apply language restrictions. We selected blinded or unblinded randomised or quasi-randomised clinical trials, reporting on adult patients with acute or acute-on-chronic cardiogenic pulmonary oedema and where NPPV (continuous positive airway pressure (CPAP) or bilevel NPPV) plus standard medical care was compared with standard medical care alone. Two authors independently selected articles and abstracted data using a standardised data collection form. We evaluated study quality with emphasis on allocation concealment, sequence generation allocation, losses to follow-up, outcome assessors, selective outcome reporting and adherence to the intention-to-treat principle. We included 32 studies (2916 participants), of generally low or uncertain risk of bias. Compared with standard medical care, NPPV significantly reduced hospital mortality (RR 0.66, 95% CI 0.48 to 0.89) and endotracheal intubation (RR 0.52, 95% CI 0.36 to 0.75). We found no difference in hospital length of stay with NPPV; however, intensive care unit stay was reduced by 1 day (WMD -0.89 days, 95% CI -1.33 to -0.45). Compared with standard medical care, we did not observe significant increases in the incidence of acute myocardial infarction with NPPV during its application (RR 1.24, 95% CI 0.79 to 1.95) or after (RR 0.70, 95% CI 0.11 to 4.26). We identified fewer adverse events with NPPV use (in particular progressive respiratory distress and neurological failure (coma)) when compared with standard medical care. NPPV in addition to standard medical care is an effective and safe intervention for the treatment of adult patients with acute cardiogenic pulmonary oedema. The evidence to date on the potential benefit of NPPV in reducing mortality is entirely derived from small-trials and further large-scale trials are needed. | J10: Asli | K10: Terverifikasi
A11: 7 | B11: S0689 | C11: PubMed | D11: 10.1016/s2213-2600(16)30093-5 | E11: Frat JP, Ragot S, Girault C, Perbet S, Prat G, Boulain T, Demoule A, Ricard JD, Coudroy R, Robert R, Mercat A, Brochard L, Thille AW | F11: Effect of non-invasive oxygenation strategies in immunocompromised patients with severe acute respiratory failure: a post-hoc analysis of a randomised trial | G11: 2016 | H11: The Lancet Respiratory Medicine | I11: The use of non-invasive ventilation is controversial in immunocompromised patients with acute respiratory failure, whereas the use of high-flow nasal cannula oxygen therapy is growing as an alternative to standard oxygen. We aimed to compare outcomes of immunocompromised patients with acute respiratory failure treated with standard oxygen with those treated with high-flow nasal cannula oxygen alone or high-flow nasal cannula oxygen associated with non-invasive ventilation. We did a post-hoc subgroup analysis in a subset of immunocompromised patients with non-hypercapnic acute respiratory failure from a multicentre, randomised, controlled trial. In the trial, patients from 23 intensive care units in France and Belgium were randomly assigned (1:1:1) to receive either standard oxygen, high-flow nasal cannula alone, or non-invasive ventilation interspaced with high-flow nasal cannula between non-invasive ventilation sessions (non-invasive ventilation group). Patients with profound neutropenia, acute-on-chronic respiratory failure, cardiogenic pulmonary oedema, shock, or altered consciousness were excluded. The primary outcome was the proportion of patients who required endotracheal intubation within 28 days after randomisation. Of the 82 immunocompromised patients, 30 were treated with standard oxygen, 26 with high-flow nasal cannula alone, and 26 with non-invasive ventilation plus interspaced high-flow nasal cannula. 8 (31%) of 26 patients treated with high-flow nasal cannula alone, 13 (43%) of 30 patients treated with standard oxygen, and 17 (65%) of 26 patients treated with non-invasive ventilation required intubation at 28 days (p=0·04). Odds ratios (ORs) for intubation were higher in patients treated with non-invasive ventilation than in those treated with high-flow nasal cannula: OR 4·25 (95% CI 1·33-13·56). ORs were not significantly different between patients treated with high-flow nasal cannula alone and standard oxygen: OR 1·72 (0·57-5·18). After multivariable logistic regression, the two factors independently associated with endotracheal intubation and mortality were age and use of non-invasive ventilation as first-line therapy. Non-invasive ventilation might be associated with an increased risk of intubation and mortality and should be used cautiously in immunocompromised patients with acute hypoxaemic respiratory failure. French Ministry of Health, the French societies of intensive care (Société de Réanimation de Langue Française, SRLF) and pneumology (Société de Pneumologie de Langue Française, SPLF), La Mutuelle de Poitiers, AADAIRC (Association pour l'Assistance à Domicile Aux Insuffisants Respiratoires Chroniques), and Fisher&Paykel Healthcare. | J11: Asli | K11: Terverifikasi
A12: 8 | B12: S1865 | C12: PubMed | D12: 10.1152/jappl.1989.66.1.288 | E12: Barrowcliffe MP, Zanelli GD, Jones JG | F12: Pulmonary clearance of radiotracers after positive end-expiratory pressure or acute lung injury | G12: 1989 | H12: Journal of Applied Physiology | I12: In anesthetized rabbits we measured clearance from lung to blood of eight aerosolized technetium-99m-labeled compounds: diethylenetriaminepentaacetate (99mTc-DTPA); cytochrome c; myoglobin; a myoglobin polymer; albumin; and anionic, cationic, and neutral dextrans of equivalent molecular size. We investigated the effect of applying positive end-expiratory pressure (PEEP) and, on a subsequent occasion, of injecting oleic acid intravenously to produce acute lung injury on the pulmonary clearance rate. Base-line clearance rates were monoexponential and varied with the molecular weights of the radiotracers. For each tracer the rate of clearance was increased a similar degree by either PEEP or oleic acid. However, with PEEP, clearance remained monoexponential, whereas after oleic acid, smaller molecular-weight radiotracers had multiexponential clearance curves. This suggests that after oleic acid the alveolar epithelium breaks down in a nonuniform fashion. We conclude that differentiation of the effect of PEEP from that of severe lung injury caused by oleic acid is not readily accomplished by either increasing the size of the tracer molecule or by varying the molecular charge. | J12: Asli | K12: Terverifikasi
A13: 9 | B13: S1472 | C13: PubMed | D13: 10.1111/eci.12908 | E13: Baratta F, Pastori D, Fabiani M, Fabiani V, Ceci F, Lillo R, Lolli V, Brunori M, Pannitteri G, Cravotto E, De Vito C, Angelico F, Del Ben M | F13: Severity of OSAS, CPAP and cardiovascular events: A follow‐up study | G13: 2018 | H13: European Journal of Clinical Investigation | I13: Previous studies suggested obstructive sleep apnoea syndrome ( OSAS ) as a major risk factor for incident cardiovascular events. However, the relationship between OSAS severity, the use of continuous positive airway pressure ( CPAP ) treatment and the development of cardiovascular disease is still matter of debate. The aim was to test the association between OSAS and cardiovascular events in patients with concomitant cardio‐metabolic diseases and the potential impact of CPAP therapy on cardiovascular outcomes. Prospective observational cohort study of consecutive outpatients with suspected metabolic disorders who had complete clinical and biochemical workup including polysomnography because of heavy snoring and possible OSAS . The primary endpoint was a composite of major adverse cardiovascular and cerebrovascular events ( MACCE ). Median follow‐up was 81.3 months, including 434 patients (2701.2 person/years); 83 had a primary snoring, 84 had mild, 93 moderate and 174 severe OSAS , respectively. The incidence of MACCE was 0.8% per year (95% confidence interval [ CI ] 0.2‐2.1) in primary snorers and 2.1% per year (95% CI 1.5‐2.8) for those with OSAS . A positive association was observed between event‐free survival and OSAS severity (log‐rank test; P = .041). A multivariable Cox regression analysis showed obesity ( HR = 8.011, 95% CI 1.071‐59.922, P = .043), moderate OSAS (vs non‐ OSAS HR = 3.853, 95% CI 1.069‐13.879, P = .039) and severe OSAS (vs non‐ OSAS HR = 3.540, 95% CI 1.026‐12.217, P = .045) as predictors of MACCE . No significant association was observed between CPAP treatment and MACCE (log‐rank test; P = .227). Our findings support the role of moderate/severe OSAS as a risk factor for incident MACCE . CPAP treatment was not associated with a lower rate of MACCE . | J13: Asli | K13: Terverifikasi
A14: 10 | B14: S1797 | C14: PubMed | D14: 10.1097/00000542-200204000-00007 | E14: Drummond GB, Stedul K, Kingshott R, Rees K, Nimmo AF, Wraith P, Douglas NJ | F14: Automatic CPAP Compared with Conventional Treatment for Episodic Hypoxemia and Sleep Disturbance after Major Abdominal Surgery | G14: 2002 | H14: Anesthesiology | I14: After major surgery, analgesia with opioids can cause obstructive apnea and intermittent hypoxemia, probably from loss of upper airway control. Since this resembles the obstructive sleep apnea syndrome, we tested the possibility that nasal continuous positive airway pressure (nCPAP) would reduce episodes of reduced oxygen saturation and sleep disruption. Because oxygen therapy is frequent after surgery, we also assessed the effect of oxygen on sleep disruption. We recruited 48 patients about to have major abdominal surgery. We present data for 34 patients: 27 who received patient-controlled intravenous morphine and 7 who received epidural opioid. Treatment was randomized to either nCPAP or conventional therapy with an oxygen mask. Alternate periods of administration of air and 35% oxygen were used in both groups. If the oxygen saturation as measured by pulse oximetry was consistently &lt;90% on air, the patient was withdrawn from the study. We measured sleep, arousals, oxygenation, episodes of desaturation, and disturbances of respiration. Values are given as median and quartiles. The median proportion of time awake was 65% (45-79%) among control patients and 74% (55-87%) among those undergoing nCPAP. Oxygen administration did not affect the sleep pattern. The median frequency of arousals per hour of sleep was very similar in each group: during air breathing from nCPAP, 125 (76-187), and during air breathing by mask, 116 (84-187). Oxygen therapy had no effect. Oxygenation and hypoxemic events were not improved by nCPAP. Oxygen therapy improved oxygenation and reduced but did not eliminate episodes of desaturation. Nasal CPAP does not improve sleep and oxygenation or reduce hypoxemic events in the first night after major abdominal surgery. | J14: Asli | K14: Terverifikasi
A15: 11 | B15: S1469 | C15: PubMed | D15: 10.1016/s0140-6736(00)03492-9 | E15: Masip J, Betbesé AJ, Páez J, Vecilla F, Cañizares R, Padró J, Paz MA, Otero Jd, Ballús J | F15: Non-invasive pressure support ventilation versus conventional oxygen therapy in acute cardiogenic pulmonary oedema: a randomised trial | G15: 2000 | H15: The Lancet | I15: Non-invasive pressure support ventilation (NIPSV) is an effective treatment for acute respiratory failure in patients with chronic obstructive pulmonary disease. We assessed the efficacy of this therapy in acute cardiogenic pulmonary oedema in a randomised comparison with conventional oxygen therapy. 40 patients were randomly assigned conventional oxygen therapy or NIPSV supplied by a standard ventilator through a face mask, with adjustment of tidal volume and pressure support in addition to a positive end-expiratory pressure of 5 cm water. Physiological measurements were obtained in the first 2 h and at 3 h, 4 h, and 10 h. The main endpoints were intubation rate and resolution time. Analyses were by intention to treat. Three patients were withdrawn on the basis of clinical and chest radiography results. Endotracheal intubation was required in one (5%) of 19 patients assigned NIPSV and in six (33%) of 18 assigned conventional oxygen therapy (p=0.037). Resolution time (defined as a clinical improvement with oxygen saturation of 96% or more and respiratory rate less than 30 breaths/min) was significantly shorter in the NIPSV group (median 30 [IQR 15-53] vs 105 [50-230] min, p=0.002). NIPSV led to a rapid improvement in oxygenation in the first 2 h. There were no differences in hospital length of stay or mortality. In this study of acute cardiogenic pulmonary oedema, NIPSV was superior to conventional oxygen therapy. Further studies should compare NIPSV with continuous positive airway pressure. | J15: Asli | K15: Terverifikasi
A16: 12 | B16: S2409 | C16: PubMed | D16: 10.1161/01.cir.0000022692.49934.e3 | E16: Al-Khatib SM, Granger CB, Huang Y, Lee KL, Califf RM, Simoons ML, Armstrong PW, Van de Werf F, White HD, Simes RJ, Moliterno DJ, Topol EJ, Harrington RA | F16: Sustained Ventricular Arrhythmias Among Patients With Acute Coronary Syndromes With No ST-Segment Elevation | G16: 2002 | H16: Circulation | I16: Background — The prognosis of ventricular arrhythmias among patients with non–ST-elevation acute coronary syndromes is unknown. We studied the incidence, predictors, and outcomes of sustained ventricular arrhythmias in 4 large randomized trials of such patients. Methods and Results — We pooled the datasets of the Global Use of Streptokinase and tPA for Occluded Arteries (GUSTO)-IIb, Platelet Glycoprotein IIb/IIIa in Unstable Angina: Receptor Suppression Using Integrilin Therapy (PURSUIT), Platelet IIb/IIIa Antagonism for the Reduction of Acute Coronary Syndrome Events in a Global Organization Network (PARAGON)-A, and PARAGON-B trials (n=26 416). We identified independent predictors of ventricular fibrillation (VF) and ventricular tachycardia (VT) and compared the 30-day and 6-month mortality rates of patients who did (n=552) and did not (n=25 864) develop these arrhythmias during the index hospitalization. Independent predictors of in-hospital VF included prior hypertension, chronic obstructive pulmonary disease, prior myocardial infarction, and ST-segment changes at presentation. Except for hypertension, these variables also independently predicted in-hospital VT. In Cox proportional-hazards modeling, in-hospital VF and VT were independently associated with 30-day mortality (hazard ratio [HR], 23.2 [95% CI, 18.1 to 29.8] for VF and HR, 7.6 [95% CI, 5.5 to 10.4] for VT) and 6-month mortality (HR, 14.8 [95% CI, 12.1 to 18.3] for VF and HR, 5.0 [95% CI, 3.8 to 6.5] for VT). These differences remained significant after excluding patients with heart failure or cardiogenic shock and those who died &lt;24 hours after enrollment. Conclusions — Despite the use of effective therapies for non–ST-elevation acute coronary syndromes, ventricular arrhythmias in this setting are associated with increased 30-day and 6-month mortality. More effective therapies are needed to improve the survival of patients with these arrhythmias. | J16: Asli | K16: Terverifikasi
... A111: 107 | B111: S1206 | C111: PubMed | D111: 10.5005/jp-journals-10071-24335 | E111: Karim HMR, Esquinas AM | F111: Ketamine Sedation for Noninvasive Ventilation in Distressed Elderly Patients with Acute Decompensated Heart Failure: Is it Safe? | G111: 2022 | H111: Indian Journal of Critical Care Medicine | I111: How to cite this article: Karim HMR, Esquinas AM. Ketamine Sedation for Noninvasive Ventilation in Distressed Elderly Patients with Acute Decompensated Heart Failure: Is it Safe? Indian J Crit Care Med 2022;26(10):1161. | J111: Asli | K111: Terverifikasi
A112: 108 | B112: S2250 | C112: PubMed | D112: 10.21203/rs.3.rs-30079/v1 | E112: Fabre M, Fehlmann CA, Gartner B, Zimmermann CG, Rey F, Sarasin F, Suppan L | F112: Association between Prehospital Arterial Hypercapnia in Acute Heart Failure and Admission to Acute Care Units: a Retrospective Cohort Study | G112: 2020 | I112: Abstract Background Acute Heart Failure (AHF) is a common condition that often manifests by acute respiratory distress and requires urgent medical evaluation and treatment. Arterial hypercapnia is common in AHF. It has been associated with a higher rate of intubation and non-invasive ventilation in the Emergency Room (ER), but its prognostic value has never been studied in the prehospital setting. Methods A retrospective study was performed on the charts of all patients taken care of by a physician-staffed prehospital mobile unit between June 2016 and September 2019 in Geneva. After approval by the ethics committee, charts were screened to identify all adult patients with a diagnosis of AHF. The main predictor was prehospital hypercapnia. The primary outcome was admission rate in an acute care unit (ACU, composite of intensive care or high-dependency units). Secondary outcomes were ER length of stay (LOS), orientation from ER (intensive care unit, high-dependency unit, general ward, discharge home), intubation rate at 24 hours, hospital LOS and hospital mortality. Results A total of 104 patients with a diagnosis of AHF were included. Hypercapnia was found in 59 (57%) patients and vital signs were more severely altered in this group. The overall ACU admission rate was 47%, with a statistically significant difference between hypercapnic and non-hypercapnic patients (58% vs 33% respectively, p = 0.014). ER LOS was shorter in hypercapnic patients (5.5 hours vs 8.9 hours, p = 0.008). Conclusions There is a significant association between prehospital arterial hypercapnia and acute care unit admission in AHF patients. | J112: Asli | K112: Terverifikasi
A113: 109 | B113: S0555 | C113: PubMed | D113: 10.1177/0885066616636021 | E113: Alaya S, Mofredj A, Tassaioust K, Bahloul H, Mrabet A | F113: Acute Parotitis as a Complication of Noninvasive Ventilation | G113: 2016 | H113: Journal of Intensive Care Medicine | I113: Several conditions, including oropharyngeal dryness, pressure sores, ocular irritation, epistaxis, or gastric distension, have been described during noninvasive ventilation (NIV). Although this technique has been widely used in intensive care units and emergency wards, acute swelling of the parotid gland remains a scarcely reported complication. We describe herein the case of an 82-year-old man who developed unilateral parotitis during prolonged NIV for acute heart failure. Intravenous antibiotics, corticosteroids, and adjusting the mask laces’ position allowed rapid resolution of clinical symptoms. | J113: Asli | K113: Terverifikasi
A114: 110 | B114: S2470 | C114: PubMed | D114: 10.1007/s00134-006-0324-1 | E114: Demoule A, Girou E, Richard JC, Taille S, Brochard L | F114: Benefits and risks of success or failure of noninvasive ventilation | G114: 2006 | H114: Intensive Care Medicine | I114: Noninvasive ventilation (NIV) fails more frequently for de novo acute respiratory failure (de novo) than for cardiogenic pulmonary edema (CPE) or acute-on-chronic respiratory failure (AOC). The impact of NIV failure and success was compared between de novo and CPE or AOC after adjustment for disease severity. Patients requiring ventilatory support were enrolled in a prospective survey in 70 French ICUs. Of 1076 patients requiring ventilatory support, 524 were eligible, including 299 de novo (NIV use, 30%) and 225 CPE-AOC (NIV use, 55%). Independent risk factors associated with mortality and length of stay were identified by logistic regression analysis. The adjusted outcome of NIV success or failure was compared to that with endotracheal intubation without NIV. NIV success was independently associated with survival in both de novo, adjusted OR 0.05 (95% CI 0.01-0.42), and CPE-AOC OR 0.03 (CI 0.01-0.24). NIV failure was associated with ICU mortality in the de novo group (OR 3.24, CI 1.61-6.53) but not in the CPE-AOC group. Nosocomial pneumonia was less common in patients successful with NIV. NIV failure was associated with a longer ICU stay in CPE-AOC only. The overall use of NIV was independently associated with a better outcome only in CPE-AOC patients (OR 0.33, CI 0.15-0.73). The effect of NIV differs between de novo and CPE-AOC patients because NIV failure is associated with increased mortality for de novo patients. This finding should raise a note of caution when applying NIV in this indication. | J114: Asli | K114: Terverifikasi
A115: 111 | B115: S0734 | C115: PubMed | D115: 10.1097/00003246-198202000-00001 | E115: NIKKI P, RÄSÄNEN J, TAHVANAINEN J, MÄKELÄINEN A | F115: Ventilatory pattern in respiratory failure arising from acute myocardial infarction. I. Respiratory and hemodynamic effects of IMV4 vs IPPV12 and PEEP0 vs PEEP10 | G115: 1982 | H115: Critical Care Medicine | I115: Positive end-expiratory pressure of 10 cm H2O (PEEP10) was compared with zero-end-expiratory pressure (PEEP0), intermittent mandatory ventilation (IMV), 4/min, with intermittent positive pressure ventilation (IPPV), 12/min, in 9 patients with pulmonary edema due to acute myocardial infarction (AMI). Systemic and pulmonary arterial pressures, pulmonary capillary wedge pressure (PCWP) and CVP, cardiac output (CO) and blood gases were measured during these four experimental interventions, and related parameters calculated. PaCO2 was 39.3 +/- 0.9 torr during IMV4 and 36.2 +/- 1.3 torr during IPPV12, and PCWP remained between 20-30 mm Hg throughout the study. The ventilatory pattern was changed at random order with the patient serving as his own control. Both PaO2 and PaO2/F102 and VO2 increased while venous admixture (Qsp/Qt) decreased with PEEP10. Cardiac and stroke indices (CI, SI) and oxygen delivery were lower with IPPV12 than they were with IMV4. Both left and right ventricular stroke work (LVSW, RVSW) were higher on IMV4. A moderate PEEP level (up to 10 cm H2O) seems beneficial in post-AMI pulmonary edema and has no significant hemodynamic side effects. The results indicate that of the four alternatives studied, IMV4 with PEEP10 is a ventilatory pattern of choice in the respiratory management of these patients, but each individual patient may require precise titration of each modality to achieve the optimal result. | J115: Asli | K115: Terverifikasi
A116: 112 | B116: S1036 | C116: PubMed | D116: 10.1097/00003246-198707000-00010 | E116: HAYEK Z, RYAN CA, EYAL F, JONES R, ARMENGOL J, KING EG, FINER NN | F116: Comparison of high-frequency chest wall compression with conventional mechanical ventilation in cats | G116: 1987 | H116: Critical Care Medicine | I116: Six anesthetized paralyzed cats with normal lungs were ventilated by high-frequency chest wall compression (HFCWC) at 5 Hz using a single-chamber circumferential cuff enclosing the thorax from the axillae to the xiphisternum. PaCO2 during HFCWC + PEEP (3 cm H2O) was significantly (p less than .0005) lower compared with conventional mechanical ventilation (CMV). End-expiratory lung volume (VL) during HFCWC + PEEP was significantly (p less than .001) lower than VL during CMV + PEEP but was higher than VL during CMV without PEEP. After the cats' lungs were stiffened by repeated saline lavage, CMV + PEEP at a mean airway pressure (Paw) of 10 cm H2O was compared with HFCWC + continuous positive airway pressure (CPAP) at an equal or lower Paw. A significant decrease in PaCO2 (p less than .02) during HFCWC occurred but no significant differences were observed in PaO2, VL, or compliance. Arterial BP and cardiac output were similar between CMV + PEEP and HFCWC + CPAP. In cats with normal lungs, VL can be maintained by applying CPAP during HFCWC, and in those with injured lungs, HFCWC + CPAP produces comparable gas exchange at a Paw equal to or lower than that used during CMV + PEEP. | J116: Asli | K116: Terverifikasi
A117: 113 | B117: S0115 | C117: PubMed | D117: 10.1007/s00380-024-02429-y | E117: Kitada S, Kawada Y, Nakasuka K, Mizoguchi T, Yamamoto J, Yokoi M, Ito T, Goto T, Kikuchi S, Seo Y | F117: Elevated arginine vasopressin levels surrogate acute lung injury in acute decompensated heart failure | G117: 2024 | H117: Heart and Vessels | I117: Activated arginine vasopressin (AVP) pathway worsens congestion in heart failure (HF), but its potential to relieve pulmonary congestion is also reported. The pathophysiological role and prognostic utility of AVP elevation in acute decompensated HF (ADHF) are poorly understood. We prospectively enrolled 52 hospitalized patients for ADHF to investigate the association between acute lung injury (ALI) in ADHF and AVP levels on admission. ALI was defined as respiratory failure leading to death, or requiring a respirator or a more than 12-h non-invasive intermittent positive pressure ventilation (NIPPV) support. In addition, we investigated the prognostic value of AVP levels on admission for cardiovascular death or recurrence of ADHF after discharge. ALI was documented in 7 patients (13.5%) during a median hospital stay of 14 days. And the patients with ALI demonstrated significantly higher AVP levels than those without (32.5 ± 21.6 vs. 6.4 ± 8.7 pg/ml, p = 0.018). Besides, the patients with ALI demonstrated significantly higher heart rates (HR) and lower E/e' on admission (HR: 127 ± 24 vs. 97 ± 28 bpm; E/e': 10.6 ± 3.7 vs. 17.4 ± 6.2, all p < 0.05, respectively). Of note, significant hemodilution assessed by hemoglobin and hematocrit values were observed in the patients with ALI 48 h after admission. A receiver operating characteristic curve analysis showed that higher than 7.2 pg/ml surrogate ALI in ADHF (AUC: 0.897, p = 0.001, Sensitivity: 85.7%, and Specificity: 77.8%). In contrast, increased AVP levels on admission could not predict cardiovascular events after discharge. Elevated AVP levels on admission are associated with ALI in ADHF but not cardiovascular events after discharge. | J117: Asli | K117: Terverifikasi
A118: 114 | B118: S2358 | C118: PubMed | D118: 10.1097/01.ccm.0000168042.59035.d8 | E118: Burns KEA, Sinuff T, Adhikari NKJ, Meade MO, Heels-Ansdell D, Martin CM, Cook DJ | F118: Bilevel noninvasive positive pressure ventilation for acute respiratory failure: Survey of Ontario practice* | G118: 2005 | H118: Critical Care Medicine | I118: OBJECTIVE: Noninvasive positive pressure ventilation (NIPPV) is commonly used in acute respiratory failure but is often applied outside evidence-based indications, particularly in low- and middle-income countries. Our objective is to assess the appropriateness of NIPPV use among internal medicine patients at a tertiary hospital in Pakistan. Appropriate use was defined as Type 1 or Type 2 respiratory failure, cardiogenic pulmonary edema, or chest wall/neuromuscular disease. Inappropriate use was defined as NIPPV applied outside standard indications. RESULTS: We conducted a cross-sectional study on 4369 patients who received NIPPV between 2019 and 2020 in the Internal Medicine unit at the Aga Khan University Hospital, Karachi. The mean age was 62.7 years, and 52.4% were male. Overall, 60.5% received NIPPV without documented respiratory failure, 21.5% had Type 1, and 18% had Type 2 failure. Metabolic acidosis accounted for 19.6% of inappropriate cases. Among Type 1 failure, pneumonia (43.1%), pulmonary edema (35.3%), and COPD (6.2%) were most common; in Type 2 failure, pulmonary edema (37.7%), pneumonia (25.8%), and COPD (15.1%) predominated. NIPPV was appropriately used in COPD and acute cardiogenic pulmonary edema but frequently applied outside evidence-based indications, particularly for metabolic acidosis. Structured protocols and research are needed on NIPPV use in LMICs. | J118: Asli | K118: Terverifikasi
A119: 115 | B119: S0400 | C119: PubMed | D119: 10.1136/pmj.78.919.257 | E119: Khurshid I, Anderson LC | F119: Non-infectious pulmonary complications after bone marrow transplantation | G119: 2002 | H119: Postgraduate Medical Journal | I119: Bone marrow transplantation (BMT) is a successful and recognised treatment option for patients with a number of haematological and non-haematological malignant and non-malignant conditions. Pulmonary complications both infectious and non-infectious are common after BMT. Multiple factors are thought to contribute to pulmonary complications, including the type and duration of immunological defects produced by the underlying disease and treatment, the development of graft-versus-host disease (GVHD), and the conditioning regimens employed. These complications are classified as early or late, depending on whether they occur before or after 100 days from transplantation. Early non-infectious pulmonary complications typically include pulmonary oedema, upper airway complications, diffuse alveolar haemorrhage, cytolytic thrombi, and pleural effusion. Bronchiolitis obliterans, veno-occlusive disease, and secondary malignancies occur late after BMT. Idiopathic pneumonia syndrome, GVHD, and radiation induced lung injury can occur in early or late period after BMT. | J119: Asli | K119: Terverifikasi
A120: 116 | B120: S2309 | C120: PubMed | D120: 10.1007/s11845-016-1456-0 | E120: Mac Donncha C, Cummins N, Hennelly D, Hannigan A, Ryan D | F120: An observational study of the utility of continuous positive airway pressure ventilation for appropriate candidates in prehospital care in the Midwest region | G120: 2016 | H120: Irish Journal of Medical Science (1971 -) | I120: Emergency medical services (EMS) practitioners in Ireland have been recently licensed to use continuous positive airway pressure (CPAP) ventilation for patients with pulmonary oedema. Both the British Thoracic Society and the Canadian Medical Association advocate the use of CPAP in hospital for patients with severe exacerbations of pulmonary oedema. The aim of this study was to identify prehospital patients in the Midwest, over a 6-month period, which could potentially benefit from CPAP if it were available in the National Ambulance Service. Potential CPAP patients were identified in the Advanced Paramedic Clinical Activity Study (APCAS) database and then followed up in the receiving hospital emergency department (ED) and medical records. Prior to this study, Irish guidance for prehospital use of CPAP did not exist and therefore the database was interrogated using a Toronto EMS Medical Directive. Descriptive analysis was conducted in Microsoft Excel and SPSS. Emergency AS1 calls (999/112) were assessed (n = 1369) and 141 patients (10.3, 95 % confidence interval 8.9-12.1 %) were identified as potential candidates for prehospital CPAP. Further investigation of ED records for 63 potential candidates found 36.5 % (95 % confidence interval 26-49 %) met the Toronto EMS criteria for CPAP. This study suggests that a suitable patient cohort for CPAP exists in the prehospital environment and highlights the need for a prospective study of CPAP use on these patients. | J120: Asli | K120: Terverifikasi
A121: 117 | B121: S0638 | C121: PubMed | D121: 10.1183/09031936.03.00039503 | E121: Saatci E, Miller DM, Stell IM, Lee KC, Moxham J | F121: Dynamic dead space in face masks used with noninvasive ventilators: a lung model study | G121: 2003 | H121: European Respiratory Journal | I121: The aim of this study was to determine what the influence of different designs of face masks and different noninvasive ventilator modes would be upon total dynamic dead space. Using a spontaneous breathing model, total dynamic dead space was measured when using 19 commercially available face masks and a range of ventilators in various ventilation modes. Total dynamic dead space during spontaneous ventilation was increased above physiological dead space from 32% to 42% of tidal volume by using face masks. The use of noninvasive ventilation modes such as bilevel and continuous positive airway pressure, with continuous pressure throughout the expiratory phase, reduced total dynamic dead space to approach physiological dead space with most face masks. Pressure assist and pressure support ventilation decreased total dynamic dead space to a lesser degree, from 42% to 39% of tidal volume. Face masks with expiratory ports over the nasal bridge resulted in beneficial flow characteristics within the face mask and nasal cavity, so as to decrease total dynamic dead space to less than physiological dead space from 42% to 28.5% of tidal volume. Exhaust ports over the nasal bridge in face masks effect important decreases in dynamic dead space provided positive pressure throughout the expiratory phase is used. | J121: Asli | K121: Terverifikasi
A122: 118 | B122: S1448 | C122: PubMed | D122: 10.1177/1479972313493795 | E122: Porhomayon J, Papadakos P, Nader ND, El-Solh AA | F122: Weaning failure: My heart is not up to it | G122: 2013 | H122: Chronic Respiratory Disease | I122: Weaning patients from mechanical ventilation has been compared to a cardiac stress test. Weaning failure (WF) from a cardiac origin can be common in patients with limited cardiac reserve. Diuretic and vasodilator therapies are indicated for WF due to excessive preload, afterload, or myocardial ischemia. Alteration in intrathoracic pressure and lung volumes may also impact weaning process in a patient with poor cardiac function. Noninvasive ventilation decreases cardiac stress load and should be utilized in weaning patients with poor cardiac reserves. In fact, positive pressure therapy is now the standard of care for treating a patient with acute pulmonary edema and to decrease afterload (Frazier et al. Biol Res Nurs 2000; 1(4): 253–264; Pinsky MR. Chest 2005; 128(5 Suppl 2): 592S–597S.). Recently, biomarkers and echocardiography have been utilized to assess weaning success during spontaneous breathing trials. In this article, we describe the physiological alterations in cardiac and pulmonary systems during the weaning process and its impact on weaning outcome. | J122: Asli | K122: Terverifikasi
A123: 119 | B123: S2393 | C123: PubMed | D123: 10.1161/01.res.0000043825.01705.1b | E123: Mann DL | F123: Inflammatory Mediators and the Failing Heart | G123: 2002 | H123: Circulation Research | I123: Recent studies have identified the importance of proinflammatory mediators in the development and progression of heart failure. The growing appreciation of the pathophysiological consequences of sustained expression of proinflammatory mediators in preclinical and clinical heart failure models culminated in a series of multicenter clinical trials that used “targeted” approaches to neutralize tumor necrosis factor in patients with moderate to advanced heart failure. However, these targeted approaches have resulted in worsening heart failure, thereby raising a number of important questions about what role, if any, proinflammatory cytokines play in the pathogenesis of heart failure. This review will summarize the tremendous growth of knowledge that has taken place in this field, with a focus on what we have learned from the negative clinical trials, as well as the potential direction of future research in this area. | J123: Asli | K123: Terverifikasi
A124: 120 | B124: S0564 | C124: PubMed | D124: 10.1177/000331978803900302 | E124: Bier AJ, Eichacker PQ, Sinoway LI, Terribile SM, Strom JA, Keefe DL | F124: Acute Cardiogenic Pulmonary Edema: Clinical and Noninvasive Evaluation | G124: 1988 | H124: Angiology | I124: Left ventricular echocardiograms performed within ninety-six hours of ad mission were prospectively correlated with the clinical course in 87 consecutive patients admitted with acute pulmonary edema. Patients were stratified into four groups based on their two-dimensional echocardiogram: hyperdynamic, normal, mildly reduced, and severely reduced. Echocardiographic estimates of left ventricular function were compared with their ejection fraction measured by the gated radioisotope technique. The authors found that 48% of the patients were either normal or hyperdynamic (38% and 10% respectively). Patients in these two groups had a greater incidence of left ventricular hypertrophy (wall thickness &gt; 13mm) (66% vs 39%, p &lt; .05), hypertension on admission (BP &gt; 160/100) (66% vs 41%, p=.05), and smaller end-diastolic dimension (p &lt; .05) than those with decreased left ventricualr function. The authors con clude that echocardiography is a good screening test of left ventricular function in patients presenting with pulmonary edema. Patients with normal or in creased left ventricular systolic function should be evaluated for correctable or treatable causes of acute pulmonary edema. | J124: Asli | K124: Terverifikasi
... A153: 149 | B153: S0848 | C153: PubMed | D153: 10.1152/jappl.1981.51.5.1287 | E153: Slutsky AS | F153: Gas mixing by cardiogenic oscillations: a theoretical quantitative analysis | G153: 1981 | H153: Journal of Applied Physiology | I153: A quantitative theoretical model of the enhanced gas mixing secondary to cardiogenic oscillations is presented based on the concept of augmented gas transport within the tracheobronchial tree (Science 209: 609, 1980). The model assumes “well-mixed” flow in the upper airways with the enhanced mixing described by Deff = Dmol + K . ud, where Deff is the effective diffusivity; Dmol, the molecular diffusivity: K, a constant; u, the root-mean-square flow; and d, the airway diameter. In the smaller airways on analysis based on Taylor laminar dispersion is used described by Deff = Dmol + (1/192) (ud)2/Dmol. The model predicts that, in dogs, cardiogenic oscillations should enhance gas mixing about 10-fold depending on the flow rates generated by the heart. Other predictions are that the augmentation of gas mixing should be greater 1) at lower lung volumes, 2) with sulfur hexafluoride vs. helium or air, 3) after peripheral airway dilation, and 4) after central airways constriction. Theoretical predictions are very close to published experimental results where available. This model should help in the development of mathematical models of gas mixing within the lungs that will include the contribution of cardiogenic oscillations. | J153: Asli | K153: Terverifikasi
A154: 150 | B154: S0021 | C154: PubMed | D154: 10.21203/rs.2.123/v1 | E154: Freund Y, Gorlick J, Cachanado M, Salhi S, Lemaitre V, Simon T, Mebazaa A | F154: Early and comprehensive care bundle in elderly for acute heart failure in the emergency department: study protocol of The ELISABETH stepped wedge cluster randomized trial | G154: 2018 | I154: Background: Acute heart failure (AHF) is one of the most common diagnoses for elderly patients in the emergency department (ED), with an admission rate higher than 80% and 1-month mortality around 10%. The European guidelines for the management of AHF are based on moderate levels of evidence, due to the lack of randomized controlled trials and the scarce evidence of any clinical added value of a specific treatment to improve outcomes. Recent reports suggest that the very early administration of full recommended therapy may decrease mortality. However, several studies highlighted that elderly patients often received suboptimal treatment. Our hypothesis is that an early care bundle that comprises early and comprehensive management of symptoms, along with prompt detection and treatment of precipitating factors should improve AHF outcome in elderly patients. Method/design: ELISABETH is a stepped-wedge, controlled cluster randomized, clinical trial in 15 emergency departments in France recruiting all patients aged 75 years and older with a diagnosis of AHF. The tested intervention is a care bundle with a checklist that mandates detection and early treatment of AHF precipitating factors, early and intensive treatment of congestion with intravenous nitrates boluses, and application of other recommended treatment (low dose diuretics, non-invasive ventilation when indicated, and preventive low molecular weight heparin). Each centre are randomized to the order in which they will switch from “control period” to “intervention period”. All centers begin the trials with the control period for two weeks, then after each two-weeks step a new centre will be in the intervention period. At the end of the trial, all clusters will receive the intervention regimen. The primary outcome is the number of days alive and out of the hospital at 30 days. Discussion: If our hypothesis is confirmed, this trial will strengthen the level of evidence of AHF guidelines and stress the importance of the associated early and comprehensive treatment of precipitating factors. This trial could be the first to report a reduction in short term morbidity and mortality in elderly AHF patients. Registration: NCT03683212, prospectively registered on September 25th 2018 Keywords: Elderly, acute heart failure, emergency department | J154: Asli | K154: Terverifikasi
A155: 151 | B155: S0903 | C155: PubMed | D155: 10.1161/01.hyp.0000013264.41234.24 | E155: Binggeli C, Corti R, Sudano I, Luscher TF, Noll G | F155: Effects of Chronic Calcium Channel Blockade on Sympathetic Nerve Activity in Hypertension | G155: 2002 | H155: Hypertension | I155: The sympathetic nervous system (SNS) is an important regulator of the circulation. Its activity is increased in hypertension and heart failure and adversely affects prognosis. Although certain drugs inhibit SNS, dihydropyridine calcium antagonists may stimulate the system. Phenylalkylamine calcium antagonists such as verapamil have a different pharmacological profile. We therefore tested the hypothesis of whether amlodipine, nifedipine, or verapamil differs in the effects on muscle sympathetic nerve activity (MSA). Forty-three patients (31 men, 12 women) with mild to moderate hypertension were randomly assigned to 1 drug for 8 weeks. Blood pressure, heart rate, and MSA (by microneurography) were measured at baseline and after 8 weeks of treatment. All calcium antagonists led to a similar decrease in blood pressure of 5.0±1.5 to 6.4±1.4 mm Hg at 8 weeks ( P &lt;0.001 versus baseline). There were no significant differences in MSA between groups. With amlodipine, MSA averaged 49±3 bursts/min (3 versus baseline); with nifedipine, 48±3 bursts/min (2 versus baseline); and with verapamil, 49±2 bursts/min (all, P =NS). With verapamil, norepinephrine decreased by 4% but tended to increase by about one third with amlodipine or nifedipine ( P =NS). Thus, in hypertension slow release forms of verapamil, nifedipine, and amlodipine exert comparable antihypertensive effects and do not change MSA, although there was a trend toward decreased MSA and plasma norepinephrine with verapamil. | J155: Asli | K155: Terverifikasi
A156: 152 | B156: S2341 | C156: PubMed | D156: 10.7326/0003-4819-152-9-201005040-00009 | E156: Weng CL, Zhao YT, Liu QH, Fu CJ, Sun F, Ma YL, Chen YW, He QY | F156: Meta-analysis: Noninvasive Ventilation in Acute Cardiogenic Pulmonary Edema | G156: 2010 | H156: Annals of Internal Medicine | I156: Noninvasive ventilation (NIV) is commonly used to treat patients with acute cardiogenic pulmonary edema (ACPE), but the findings of a recent large clinical trial suggest that NIV may be less effective for ACPE than previously thought. To provide an estimate of the effect of NIV on clinical outcomes in patients with ACPE that incorporates recent trial evidence and explore ways to interpret that evidence in the context of preceding evidence that favors NIV. PubMed and EMBASE from 1966 to December 2009, Cochrane Central Register of Controlled Trials and conference proceedings through December 2009, and reference lists, without language restriction. Randomized trials that compared continuous positive airway pressure and bilevel ventilation with standard therapy or each other. Two independent reviewers extracted data. Outcomes examined were mortality, intubation rate, and incidence of new myocardial infarction (MI). Compared with standard therapy, continuous positive airway pressure reduced mortality (relative risk [RR], 0.64 [95% CI, 0.44 to 0.92]) and need for intubation (RR, 0.44 [CI, 0.32 to 0.60]) but not incidence of new MI (RR, 1.07 [CI, 0.84 to 1.37]). The effect was more prominent in trials in which myocardial ischemia or infarction caused ACPE in higher proportions of patients (RR, 0.92 [CI, 0.76 to 1.10] when 10% of patients had ischemia or MI vs. 0.43 [CI, 0.17 to 1.07] when 50% had ischemia or MI). Bilevel ventilation reduced the need for intubation (RR, 0.54 [CI, 0.33 to 0.86]) but did not reduce mortality or new MI. No differences were detected between continuous positive airway pressure and bilevel ventilation on any clinical outcomes for which they were directly compared. The quality of the evidence base was limited. Definitions, cause, and severity of ACPE differed among the trials, as did patient characteristics and clinical settings. Although a recent large trial contradicts results from previous studies, the evidence in aggregate still supports the use of NIV for patients with ACPE. Continuous positive airway pressure reduces mortality more in patients with ACPE secondary to acute myocardial ischemia or infarction. None. | J156: Asli | K156: Terverifikasi
A157: 153 | B157: S1285 | C157: PubMed | D157: 10.1155/2015/846234 | E157: Kasemsap N, Netwijitpan S, Limpawattana P, Kongbunkiat K, Tiamkao S, Chotmongkol V, Aekphachaisawat N, Sawanyawisuth K | F157: CPAP Therapy Improves Intractable Hemifacial Spasm | G157: 2015 | H157: Case Reports in Neurological Medicine | I157: The correlation between obstructive sleep apnea (OSA) and hemifacial spasm has never been reported in the literature. Here, we report a case of OSA-induced hypertension with intractable hemifacial spasm in which both conditions improved after continuous positive airway pressure treatment. | J157: Asli | K157: Terverifikasi
A158: 154 | B158: S2344 | C158: PubMed | D158: 10.3390/diagnostics15141765 | E158: Barbieri G, Del Carlo C, D’Angelo G, Deri C, Cipriano A, De Carlo P, Santini M, Ghiadoni L | F158: Diagnostic and Prognostic Value of Lung Ultrasound Performed by Non-Expert Staff in Patients with Acute Dyspnea | G158: 2025 | H158: Diagnostics | I158: Background/Objectives: Dyspnea is one of the main causes of visits to the Emergency Department (ED) and hospitalization, with its differential diagnosis representing a challenge for the clinician. Lung ultrasound (LUS) is a widely used tool in ED. The objective of this study was to evaluate the impact of LUS, performed by a non-expert operator, in determining diagnosis and prognosis of patients with dyspnea. Methods: A total of 60 patients presenting with dyspnea at the ED were prospectively enrolled and underwent LUS examination by a medical student, after brief training, within 3 h of triage. LUS findings were classified into four patterns: N.1, absence of notable ultrasound findings, attributable to COPD/ASMA exacerbation; N.2, bilateral interstitial syndrome, suggestive of acute heart failure; N.3, subpleural changes/parenchymal consolidations, suggestive of pneumoniae; and N.4, isolate polygonal triangular consolidation, attributable to infarction in the context of pulmonary thromboembolism. Results: The diagnostic hypothesis formulated after LUS was compared with the final diagnosis after further investigations in the ED, showing agreement in 90% of cases. The mean LUS score value was higher in patterns N.2 (18.4 ± 8.5) and N.3 (17 ± 6.6), compared to patterns N.1 and N.4 (9.8± 6.7 and 11.5 ± 2.1). Given the high prevalence of pattern N.2, the diagnostic accuracy of LUS in this context was further evaluated, showing a sensitivity of 82% and specificity of 100%. In terms of the prognostic value of LUS, hospitalized patients had a higher LUS score compared to those discharged (17.3 ± 8.1 vs. 8.5 ± 6.8, p value 0.004). A similar trend was obtained in the subgroup of patients requiring non-invasive ventilation (NIV), who present a higher LUS score (21.1 ± 6.6 vs. 13.1 ± 8.1, p value 0.002). When considering a combined outcome (death and NIV), patients with worse outcomes more often had a LUS score &gt; 15 (p value &lt; 0.001). Conclusions: In conclusion, this study confirms that LUS is a very useful tool in the ED, assisting the clinical evaluation for diagnosis, treatment decision, and determination of the appropriate care setting for patients with acute dyspnea. Its short learning curve allows even non-expert staff to use it effectively. | J158: Asli | K158: Terverifikasi
A159: 155 | B159: S1307 | C159: PubMed | D159: 10.1378/chest.128.2.587 | E159: de Llano LAP, Golpe R, Piquer MO, Racamonde AV, Caruncho MV, Muinelos OC, Carro CA | F159: Short-term and Long-term Effects of Nasal Intermittent Positive Pressure Ventilation in Patients With Obesity-Hypoventilation Syndrome | G159: 2005 | H159: Chest | I159: Acute hypercapnic respiratory failure (AHRF) is a common life-threatening event in patients with obesity hypoventilation syndrome (OHS). To study the clinical pattern, noninvasive ventilatory support, as well as the short- and long-term outcomes of patients with OHS admitted in a ward because of AHRF. We conducted a retrospective cohort study including all adults with OHS aged ≥ 18 - year - old, admitted in a 90-bed-ward for AHRF. A total of 44 patients were included. Fifteen (34.1%) and 29 (65.9%) patients were diagnosed with malignant OHS (mOHS) and nonmalignant OHS (non-mOHS), respectively, while 36 (81.8%) had coexisting obstructive sleep apnea hypopnea syndrome (OSAHS). Patients with mOHS had a significantly higher rate of heart failure (100% vs. 31%; p < 0.001), chronic renal insufficiency (CRI) (73.3% vs. 41.4%; p = 0.04), and dyslipidemia (66.7% vs. 34.5%; p = 0.04) than those with non-mOHS. The mean forced vital capacity (FVC) in our patients was of 59.5% ± 18.5 of the predicted value, lower than what is usually reported in stable patients with OHS. At hospital admission, more than two-thirds (n = 34, 77.3%) were misdiagnosed as having asthma exacerbation (n = 4, 4.9.1%), chronic obstructive pulmonary disease (COPD) exacerbation (n = 12, 27.3%) and/or heart failure (n = 29, 65.9%). Acute pulmonary oedema (ACPE) (n = 16, 36.4%) and acute viral bronchitis (n = 12, 27.3%) were the main identified causal factors, while no cause could be determined in 5 (11.4%) patients. Noninvasive positive pressure ventilation (NIPPV) using bilevel positive airway pressure (BIPAP) was very highly effective to treat AHRF, with only 2.27% of patients failing the modality. Median overall duration of ventilation was 9 hours per day (1.3-20) and was significantly longer in patients with mOHS than in those with non-mOHS (10 [6-18] vs. 8 [1.3-20], respectively; p = 0.01). Forty two of the forty-three patients discharged alive were treated with BIPAP or continuous positive airway pressure (CPAP) in 26 and 16 patients, respectively. The probability of survival was 90% at 12 months, while the probability of readmission for a new episode of AHRF was 56% at 6 months and 22% at 12 months, respectively. AHRF in OHS patients is a life-threatening event which can be successfully and safely treated with BIPAP, with a low long-term mortality even in patients with mOHS. | J159: Asli | K159: Terverifikasi
A160: 156 | B160: S0969 | C160: PubMed | D160: 10.1186/s13049-016-0288-2 | E160: Laursen CB, Hänselmann A, Posth S, Mikkelsen S, Videbæk L, Berg H | F160: Prehospital lung ultrasound for the diagnosis of cardiogenic pulmonary oedema: a pilot study | G160: 2016 | H160: Scandinavian Journal of Trauma, Resuscitation and Emergency Medicine | I160: Noninvasive ventilation (NIV) improves the outcome of acute cardiogenic pulmonary edema (AcPE) and acute exacerbation of chronic obstructive pulmonary disease (aeCOPD) but is not recommended in pneumonia. The aim of this study was to assess the appropriateness of the use of NIV in a prehospital setting, where etiological diagnostics rely mainly on clinical examination. This observational multicenter retrospective study included all the patients treated with NIV by three mobile medical emergency teams in 2015. Prehospital diagnoses and hospital diagnoses were extracted from the medical charts. The appropriateness of NIV was determined by matching the hospital diagnosis to the current guidelines. Among the 14,067 patients screened, 172 (1.2%) were treated with NIV. The more frequent prehospital diagnoses were AcPE (n = 102, 59%), acute respiratory failure of undetermined cause (n = 46, 28%) and aeCOPD (n = 17, 10%). An accurate prehospital diagnosis was more frequent for AcPE (83/88, 94%) than for aeCOPD (14/32, 44%; p < 0.01). Only two of the 25 (8%) pneumonia cases were diagnosed during prehospital management. Prehospital NIV was inappropriate for 32 (21%) patients. Patients with inappropriate NIV had a higher rate of in-hospital intubation than patients with appropriate NIV (38% vs. 8%; p < 0.001). This high frequency of inappropriate NIV could be reduced by an improvement in the prehospital detection of aeCOPD and pneumonia. | J160: Asli | K160: Terverifikasi
A161: 157 | B161: S1044 | C161: PubMed | D161: 10.20452/pamw.705 | E161: Potts JM | F161: Noninvasive positive pressure ventilation Effect on mortality in acute cardiogenic pulmonary edema: a pragmatic meta‑analysis | G161: 2009 | H161: Polish Archives of Internal Medicine | I161: Introduction In contrast to a series of recent meta-analyses (MAs), the 3CPO (Three Interventions in Cardiogenic Pulmonary Oedema) randomized controlled trial (RCT) reported in 2008 did not find a significant mortality benefit of noninvasive positive pressure ventilation (NPPV) in acute cardiogenic pulmonary edema (ACPE). Objectives This paper combines data collected in the 3CPO trial together with data from recent MAs and calculates a revised risk ratio for NPPV in ACPE. Reasons for the discrepancy in mortality estimates are identified and discussed through contrasting the methodology and results of the 3CPO trial with previous RCTs. Patients and methods Patients included adults with ACPE secondary to a variety of insults such as hypertension, acute coronary syndromes, dietary indiscretion, arrhythmias and valvular lesions and assessed by clinical parameters (respiratory rate, crackles, oxygen saturation) and chest radiograph. Data was collected from MAs published after 2005 and their respective RCTs. As opinions regarding RCTs worthy of inclusion in the analyses were varied, 3 sets of RCTs were combined with the 3CPO data. The first set of data duplicated the RCTs chosen in the Cochrane; the second set, a comprehensive set, included all RCTs cited in any of the MAs reviewed; and the third set, a high quality RCT set, assessed data from only those RCTs included in at least 4 out of the 5 MAs reviewed. Data were analyzed with both fixed and variable effect modes using Revman software. Results All combinations of RCTs and modes of analysis predict a significant mortality benefit. The combined data predicts a risk ratio for mortality using NPPV of 0.75 (95% CI: 0.61-0.92). Conclusions An analysis of the existing RCT data, inclusive of the 3CPO trial, predicts a continued and significant mortality benefit of NPPV in ACPE. | J161: Asli | K161: Terverifikasi
A162: 158 | B162: S0739 | C162: PubMed | D162: 10.1161/01.cir.0000041428.99427.06 | E162: Gitt AK, Wasserman K, Kilkowski C, Kleemann T, Kilkowski A, Bangert M, Schneider S, Schwarz A, Senges J | F162: Exercise Anaerobic Threshold and Ventilatory Efficiency Identify Heart Failure Patients for High Risk of Early Death | G162: 2002 | H162: Circulation | I162: Background— The maximal oxygen uptake (peak V̇ o 2 ) is used in risk stratification of patients with chronic heart failure (CHF). Peak V̇ o 2 might be lower than maximally possible if exercise is stopped early because of lack of patient motivation or premature cessation by the investigator. In contrast, the anaerobic threshold (V̇ o 2 AT) and the ventilatory efficiency (V̇ e versus V̇ co 2 slope) are less subject to these influences. Thus, we compared these parameters with peak V̇ o 2 in identifying patients with CHF at increased risk for death within 6 months after evaluation. Methods and Results— We performed cardiopulmonary exercise tests with gas exchange measurements in 223 consecutive patients with CHF (114 coronary artery disease, 92 dilated cardiomyopathy, 17 others) at the Herzzentrum Ludwigshafen between 1995 and 1998. We measured peak V̇ o 2 , V̇ o 2 AT and V̇ e versus V̇ co 2 slope. We selected peak V̇ o 2 of ≤14 mL/kg per minute, V̇ o 2 AT of &lt;11 mL/kg per minute, and V̇ e versus V̇ co 2 slope of &gt;34 as threshold values for high risk of death. The median follow-up time was 644 days. Patients with peak V̇ o 2 of ≤14 mL/kg per minute had a &gt;3-fold-increased risk (OR=3.4; CI, 1.3 to 9.1), with V̇ o 2 AT &lt;11 mL/min per kg or V̇ e versus V̇ co 2 slope &gt;34 a 5-fold increased risk for early death (OR=5.3; CI, 1.5 to 19.0; OR=4.8; CI, 1.7 to 13.8, respectively). In patients with both V̇ o 2 AT &lt;11 mL/kg per minute and V̇ e versus V̇ co 2 slope &gt;34, the risk of early death was 10-fold higher (OR=9.6; CI, 2.1 to 44.7). After correction for age, sex, left ventricular ejection fraction, and New York Heart Association class in a multivariate analysis, the combination of V̇ o 2 AT &lt;11 mL/kg per minute and V̇ e versus V̇ co 2 slope &gt;34 was the best predictor of 6-month mortality (RR=5.1, P =0.001). Conclusions— V̇ o 2 AT of &lt;11 mL/kg per minute and slope of V̇ e versus V̇ co 2 &gt;34, combined, better identified patients at high risk for early death from CHF than did peak V̇ o 2 and should therefore be considered when prioritizing patients for heart transplantation. | J162: Asli | K162: Terverifikasi
A163: 159 | B163: S0074 | C163: PubMed | D163: 10.1046/j.1440-1827.1999.00817.x | E163: Katoh M, Shigematsu H | F163: Leiomyosarcoma of the heart and its pulmonary metastasis, both with prominent osteoclast‐like multinucleated giant cells expressing tartrate‐resistant acid phosphatase activity | G163: 1999 | H163: Pathology International | I163: An autopsy case of cardiac leiomyosarcoma and its pulmonary metastasis, both with osteoclast‐like multinucleated giant cells (OMGC) mimicking the so‐called giant cell variant of malignant fibrous histiocytoma (MFH), is reported. The patient, a 70‐year‐old male, was admitted for sudden dyspnea. Extensive work‐up established only a left atrial tumor mass. Three months after admission, the patient developed multiple intracranial and pulmonary metastases, followed by a worsening clinical course characterized by semicoma and dyspnea, and subsequently died 6 months after the onset of his symptoms. At subsequent autopsy, the left atrial polypoid tumor was found to have invaded destructively to the left half of the cardiac wall. Histology of the cardiac tumor revealed a bimorphic sarcoma in which a poorly differentiated leiomyosarcoma comfirmed by histologic and immunohistochemical findings was juxtaposed to a small nodule with features closely mimicking giant cell MFH. The pulmonary metastatic nodules exhibited features that were entirely indistinguishable from giant cell MFH except for the fact that a minority of polymorphic cells manifested myogenic differentiation. We believe that such a MFH‐like pattern represents a pleomorphic form of leiomyosarcoma rather than a dedifferentiated one. The OMGC within the MFH‐like component coexpressed CD68 and tartrate‐resistant acid phosphatase activity. | J163: Asli | K163: Terverifikasi
A164: 160 | B164: S2053 | C164: PubMed | D164: 10.1177/0194599811415823a465 | E164: Lin FY, Popelka G, Gurgel R, Capasso R | F164: The Effect of CPAP on Middle Ear Pressure | G164: 2011 | H164: Otolaryngology–Head and Neck Surgery | I164: While continuous positive airway pressure (CPAP) is commonly used for obstructive sleep apnea treatment, its effect on middle ear pressure is unknown. The purpose of this study is to measure the effect of CPAP on middle ear pressure and describe the correlation between CPAP levels and middle ear pressures. This is a prospective cohort study conducted in January, 2011. 10 volunteers with no known history of Eustachian tube dysfunction or obstructive sleep apnea had standard tympanometry measurements while wearing a CPAP device. Measurements were taken at baseline and with CPAP air pressures of 5, 10, and 15 cm H20. Prior to a swallowing maneuver to open the Eustachian tube, average middle ear pressures were 21.67 daPA, 22.63 daPA, 20.42, daPA, and 21.58 daPA with CPAP pressures of 0, 5, 10, and 15cm of H20, respectively. After swallowing, average middle ear air pressures were 18.83 daPa, 46.75 daPa, 82.17 daPa, and 129.17 daPa with CPAP pressures of 0, 5, 10, and 15cm of H20, respectively. The post‐swallow Pearson Correlation Coefficient correlating CPAP and middle ear pressures was 0.783 ( P &lt;. 001). Middle ear air pressure is directly proportional to CPAP air pressure in subjects with normal Eustachian tube function. While further investigation is necessary, there may be otologic implications for patients who are chronically CPAP dependant. These findings may also influence the perioperative practice of otologic and skull base surgeons. | J164: Asli | K164: Terverifikasi
A165: 161 | B165: S0597 | C165: PubMed | D165: 10.1016/s0140-6736(75)92554-4 | E165: Siebke H, Rød T, Breivik H, Lind B | F165: SURVIVAL AFTER 40 MINUTES' SUBMERSION WITHOUT CEREBRAL SEQUELÆ | G165: 1975 | H165: The Lancet | I165: Cardiopulmonary resuscitation and rewarming were successful in a 5-year-old boy who had been submerged for 40 minutes in ice-cold fresh water. Severe metabolic acidosis was corrected by intravenous infusion of sodium bicarbonate solution before spontaneous circulation could be re-established. Fulminant pulmonary oedema developed after re-establishment of spontaneous circulation. This was efficiently reversed by positive-end-expiratory-pressure ventilation. During 2 days of treatment of a respiratory the patient gradually regained consciousness; the endotracheal tube was then removed and the patient immediately started talking intelligently. The patient went through a period of slow cerebration and motor dysfunction but recovered rapidly, and on examination 13 months after the accident all findings were normal. | J165: Asli | K165: Terverifikasi
A166: 162 | B166: S0109 | C166: PubMed | D166: 10.1111/j.1365-2796.2007.01765.x | E166: Budweiser S, Riedl SG, Jörres RA, Heinemann F, Pfeifer M | F166: Mortality and prognostic factors in patients with obesity‐hypoventilation syndrome undergoing noninvasive ventilation | G166: 2007 | H166: Journal of Internal Medicine | I166: Objectives. The incidence of obesity‐hypoventilation syndrome (OHS) has greatly increased over time, but data on long‐term outcome are limited. We investigated survival and prognostic factors in these patients undergoing noninvasive positive pressure ventilation (NPPV). Design. Retrospective descriptive analysis of patients with OHS and NPPV up to 10 years. Methods. Long‐term mortality and predictors of survival were assessed. Additionally, we evaluated changes in lung function, blood gas and laboratory parameters 5.7 ± 2.5 months after initiation of NPPV. Results. 126 patients (BMI 44.6 ± 7.8 kg m −2 ; PaCO 2 55.5 ± 7.7 mmHg) were followed for 41.3 ± 27.6 months. Upon follow‐up, blood gases (daytime and nighttime), as well as pulmonary function improved, whilst haemoglobin and BMI decreased ( P &lt; 0.001 each). Adherence to NPPV was high (94.5% continuing NPPV 6.5 ± 2.3 h day −1 ). All‐cause mortality was 12.7%, with 1‐, 2‐ and 5‐year survival of 97.1%, 92.0% and 70.2%, respectively. In univariate analysis, patients with PaO 2 &lt;50 mmHg, C‐reactive protein ≥ 5.1 mg L −1 , leucocytes ≥ 7.8 × 10 3 μ l −1 , or pH ≥ 7.44 at baseline had poor prognosis ( P &lt; 0.05 each). In Cox multivariate analysis, PaO 2 , pH and leucocytes were independent predictors of mortality. Reduction in nocturnal PaCO 2 by ≥23.0% and haemoglobin at follow‐up was associated with improved survival ( P &lt; 0.05 each) whilst a decrease in pH was a predictor of increased mortality. In contrast, neither baseline BMI nor its change was linked to survival. Conclusion. Gas exchange and lung function in OHS were improved after initiation of NPPV. Hypoxemia, high pH and elevated inflammation markers predicted poor survival. Overall, NPPV was well tolerated and survival was excellent when compared with data from historical matched controls. | J166: Asli | K166: Terverifikasi
... A177: 173 | B177: S0037 | C177: PubMed | D177: 10.1046/j.1365-2362.2001.00774.x | E177: Pham I, Andrivet P, Sediame S, Defouilloy C, Moutereau S, Wirquin V, Chouaïd C, Housset B, Adnot S | F177: Increased erythropoietin synthesis in patients with COLD or left heart failure is related to alterations in renal haemodynamics | G177: 2001 | H177: European Journal of Clinical Investigation | I177: The mechanisms controlling erythropoietin (EPO) synthesis by the kidney in patients with chronic obstructive lung disease (COLD) or congestive left heart failure (CLHF) remain incompletely understood. Renal dysfunction occurs as a consequence of decreased renal blood flow (RBF) in these diseases. Because alterations in renal haemodynamics may affect EPO synthesis and red blood cell production, we investigated the potential relationships between renal function and plasma EPO synthesis in patients with COLD or CLHF . Thirty‐two patients with COLD and 13 with CLHF underwent determination of renal physiology parameters, plasma EPO levels and haemoglobin levels. Plasma EPO concentrations were increased in patients with COLD or CLHF as compared to normal subjects, and were inversely correlated to haemoglobin concentrations. In patients with COLD or CLHF, plasma EPO was negatively correlated with both RBF and renal oxygen delivery (ROD) and positively correlated with filtration fraction. Plasma EPO was not correlated with glomerular filtration rate, fractional excretion of sodium, P o 2 or P co 2 . Among the patients with COLD, those with polycythemia (haemoglobin &gt; 150 g L −1 ) had lower plasma EPO and higher RBF and ROD values than those with normocythemia (haemoglobin ≤ 150 g L −1 ). Taken together, our data suggest that in patients with COLD or CLHF the critical determinant for EPO production is impairment of renal haemodynamics. | J177: Asli | K177: Terverifikasi
A178: 174 | B178: S2352 | C178: PubMed | D178: 10.1101/2021.10.17.21265081 | E178: Howard I, Castle N, Al Shaikh L, Owen R | F178: Safety and efficacy of a prehospital initiated protocol of nitrates plus non-invasive ventilation on prehospital and Emergency Department outcomes for acute cardiogenic pulmonary oedema | G178: 2021 | I178: Acute heart failure is a common presentation to Emergency Departments (ED) the world over. Amongst the most common presenting signs and symptoms is dyspnoea due to acute pulmonary oedema, a life-threatening emergency that if left untreated or poorly managed. There is increasing evidence demonstrating improved outcomes following the use of vasodilators or non-invasive ventilation for these patients in the emergency setting. Consequently, the potential exists that initiating these therapies in the prehospital setting will similarly improve outcomes. A historical cohort study was conducted to assess the effect of a prehospital initiated treatment protocol of nitrates plus non-invasive ventilation (NIV) versus regular therapy for severe cardiogenic APO on all-cause in-hospital mortality at 7 days, 30 days, and in total. Secondary outcomes included changes in EMS respiratory and haemodynamic parameters; admission status; length of stay; and emergency endotracheal intubation. The intervention led to an approximate 85% reduction in adjusted odds of mortality at 7 days compared to the regular therapy (AOR 0.15, 95% CI: 0.05 – 0.46, p = 0.001); approximate 80% reduction in odds of mortality at 30 days (AOR 0.19, 95% CI: 0.07 – 48, p &lt; 0.0001); and Approximate 60% reduction in odds of total mortality (AOR 0.25, 95% CI: 0.12 – 0.56, p = 0.001). The results of this analysis provide strong evidence of the potential synergistic benefits that can be achieved with the early implementation of a simple treatment protocol of prehospital administered nitrates and initiation of NIV for cardiogenic APO. | J178: Asli | K178: Terverifikasi
A179: 175 | B179: S0943 | C179: PubMed | D179: 10.1046/j.1365-2796.1999.00520.x | E179: Rydén‐Bergsten T, Andersson F | F179: The health care costs of heart failure in Sweden | G179: 1999 | H179: Journal of Internal Medicine | I179: Abstract. Rydén‐Bergsten T, Andersson F (AstraZeneca R&amp;D, Lund; and AstraZeneca R&amp;D, Mölndal; Sweden). The health care costs of heart failure in Sweden. J Intern Med 1999; 246: 275–284. Aim. Heart failure is a common and serious condition requiring extensive health care resources. The aim of this study is to estimate the total treatment costs of heart failure in Sweden. Methods and results. The study is a prevalence‐based cost‐of‐illness study. It includes costs of institutional care (hospitals and nursing homes), outpatient care, surgery and drugs. The costs are estimated based on official Swedish statistics, and on various clinical and epidemiological studies. The results are expressed in 1996 prices. The total annual treatment costs for heart failure are approximately Swedish kronor (SEK) 2000–2600 million , or nearly 2% of the Swedish health care budget. Institutional care is the single largest component, amounting to SEK 1300–1900 million , or about 65–75% of the costs of heart failure treatment. Conclusions. The results from this study indicate that heart failure is a costly condition. Efforts to develop effective management programmes that can reduce the need for expensive institutional care, without a negative impact on quality of life, morbidity and mortality, should be given high priority. | J179: Asli | K179: Terverifikasi
A180: 176 | B180: S0635 | C180: PubMed | D180: 10.1186/s12931-019-1150-7 | E180: Rotty MC, Mallet JP, Suehs CM, Martinez C, Borel JC, Rabec C, Bourdin A, Molinari N, Jaffuel D | F180: Is the 2013 American Thoracic Society CPAP-tracking system algorithm useful for managing non-adherence in long-term CPAP-treated patients? | G180: 2019 | H180: Respiratory Research | I180: Whereas telemedicine usage is growing, the only clinical algorithm for Continuous Positive Airway Pressure (CPAP) adherence management is that stipulated by the 2013 American Thoracic Society (ATS). The capacity of the latter to predict non-adherence in long-term CPAP-treated patients has not been validated. Patients from the prospective real-life InterfaceVent study (NCT03013283, study conducted in an adult cohort undergoing at least 3 months of CPAP) and eligible for ATS algorithm usage were analysed. The residual device Apnea–Hypopnea-Index (AHI flow ) and High Large Leak (HLL) thresholds proposed in the ATS algorithm were evaluated for predicting adherence (i.e. AHI flow &gt; 10/h, HLLs 95th &gt; 24 L/min for ResMed® devices and ResMed® nasal mask, HLLs 95th &gt; 36 l/min for ResMed® devices and ResMed® oronasal masks, HLLs &gt; 1 h for Philips® devices and HHLs &gt; 60 l/min for Fisher &amp; Paykel® devices). Adherence was defined according to the 2013 ATS algorithm (i.e. CPAP use &gt; 4 h/j for at least 70% of days). 650/1484 patients eligible for ATS algorithm usage were analysed (15.38% non-adherent, 74% male with a median (IQ 25–75 ) age of 68 (61–77) years, a body mass index of 30.8 (27.7–34.5) kg/m 2 , an initial AHI of 39 (31–55) events/h, and CPAP-treatment-duration of 5.1 (2.2–7.8) years). Logistic regression analysis demonstrated no significant relationship between the ATS proposed AHI flow or HLL thresholds and non-adherence. Complementary ROC curve analysis failed to determine satisfactory AHI flow and HLL thresholds. When managing non-adherence in long-term CPAP-treated patients, our data do not validate absolute AHI flow or HLL thresholds in general. The INTERFACE-VENT study is registered on ClinicalTrials.gov (Identifier: study ( NCT03013283 ). | J180: Asli | K180: Terverifikasi
A181: 177 | B181: S1287 | C181: PubMed | D181: 10.1183/09031936.02.00263102 | E181: Thys F, Liistro G, Dozin O, Marion E, Rodenstein DO | F181: Determinants ofFi,O2with oxygen supplementation during noninvasive two-level positive pressure ventilation | G181: 2002 | H181: European Respiratory Journal | I181: To maintain arterial oxygen saturation ( S a,O 2 ) above 90% in patients with acute respiratory failure, oxygen (O 2 ) is often added to the circuit of two-level noninvasive positive pressure ventilation (NPPV). However, the final inspiratory oxygen fraction ( F i,O 2 ) is not known. To clarify this issue, the effect of different inspiratory positive airway pressures (IPAP) of the oxygen tubing connection site and the flow rate of O 2 , on F i,O 2 was assessed. The effects of the tidal volume ( V T ) and the respiratory rate on the F i,O 2 were then clarified in a model study. The F i,O 2 varied depending on the point where O 2 was added to the circuit. When all other variables were constant, the connection closest to the exhaust port (ventilator side) gave the highest F i,O 2 . Increases in IPAP led to decreases in F i,O 2 . Finally, F i,O 2 increased with O 2 flow, although it was difficult to obtain an F i,O 2 &gt;0.30 unless very high O 2 flows were used. Paradoxically, NPPV with low IPAP values and without O 2 supplementation led to a F i,O 2 &lt;0.21 at the circuit-patient interface. V T and respiratory rate did not appear to influence F i,O 2 . To conclude, when using noninvasive positive pressure ventilation with two-level respirators, oxygen should be added close to the exhaust port (ventilator side) of the circuit. If inspiratory airway pressure levels are &gt;12 cmH 2 O, oxygen flows should be at least 4 L·min −1 . | J181: Asli | K181: Terverifikasi
A182: 178 | B182: S0995 | C182: PubMed | D182: 10.1152/jappl.1998.84.2.661 | E182: Lauzon AM, Elliott AR, Paiva M, West JB, Prisk GK | F182: Cardiogenic oscillation phase relationships during single-breath tests performed in microgravity | G182: 1998 | H182: Journal of Applied Physiology | I182: Lauzon, Anne-Marie, Ann R. Elliott, Manuel Paiva, John B. West, and G. Kim Prisk. Cardiogenic oscillation phase relationships during single-breath tests performed in microgravity. J. Appl. Physiol. 84(2): 661–668, 1998.—We studied the phase relationships of the cardiogenic oscillations in the phase III portion of single-breath washouts (SBW) in normal gravity (1 G) and in sustained microgravity (μG). The SBW consisted of a vital capacity inspiration of 5% He-1.25% sulfurhexafluoride-balance O 2 , preceded at residual volume by a 150-ml Ar bolus. Pairs of gas signals, all of which still showed cardiogenic oscillations, were cross-correlated, and their phase difference was expressed as an angle. Phase relationships between inspired gases (e.g., He) and resident gas (N 2 ) showed no change from 1 G (211 ± 9°) to μG (163 ± 7°). Ar bolus and He were unaltered between 1 G (173 ± 15°) and μG (211 ± 25°), showing that airway closure in μG remains in regions of high specific ventilation and suggesting that airway closure results from lung regions reaching low regional volume near residual volume. In contrast, CO 2 reversed phase with He between 1 G (332 ± 6°) and μG (263 ± 27°), strongly suggesting that, in μG, areas of high ventilation are associated with high ventilation-perfusion ratio (V˙a/Q˙). This widening of the range ofV˙a/Q˙in μG may explain previous measurements (G. K. Prisk, A. R. Elliott, H. J. B. Guy, J. M. Kosonen, and J. B. West. J. Appl. Physiol. 79: 1290–1298, 1995) of an overall unaltered range ofV˙a/Q˙in μG, despite more homogeneous distributions of both ventilation and perfusion. | J182: Asli | K182: Terverifikasi
A183: 179 | B183: S0006 | C183: PubMed | D183: 10.1016/s1388-9842(01)00141-6 | E183: Hassapoyannes CA, Easterling BM, Chavda K, Chavda KK, Movahed MR, Welch GW | F183: The Effect of Chronic Digitalization on Pump Function in Systolic Heart Failure | G183: 2001 | H183: European Journal of Heart Failure | I183: Short- and intermediate-term use of cardiac glycosides promotes inotropy and improves the ejection fraction in systolic heart failure. To determine whether chronic digitalization alters left ventricular function and performance. Eighty patients with mild-to-moderate systolic heart failure (baseline ejection fraction ≤ 45%) participated from our institution in a multi-center, chronic, randomized, double-blind study of digitalis vs. placebo. Of the 40 survivors, 38 (20 allocated to the digitalis arm and 18 to the placebo arm) were evaluated at the end of follow-up (mean, 48.4 months). Left ventricular systolic function was assessed by both nuclear ventriculography and echocardiography. The ejection fraction was measured scintigraphically, while the ventricular volumes were computed echocardiographically. The groups did not differ, at baseline or end-of-study, with respect to the ejection fraction and the loading conditions (arterial pressure, ventricular volumes and heart rate) by either intention-to-treat or actual-treatment-received analysis. Over the course of the trial, the digitalis arm exhibited no significant increase in the use of diuretics (18%, P - 0.33), in distinction from the placebo group (78%, P - 0.004), and a longer stay on study drug among those patients who withdrew from double-blind treatment (28.6 vs. 11.4 months, P - 0.01). Following chronic use of digitalis for mild-to-moderate heart failure, cross-sectional comparison with a control group from the same inception cohort showed no appreciable difference in systolic function or performance. Thus, the suggested clinical benefit cannot be explained by an inotropic effect. | J183: Asli | K183: Terverifikasi
A184: 180 | B184: S0439 | C184: PubMed | D184: 10.1183/09031936.97.10081922 | E184: Lin M, Liaw M, Huang C, Chuang M, Tsai Y | F184: Bilateral diaphragmatic paralysis--a rare cause of acute respiratory failure managed with nasal mask bilevel positive airway pressure (BiPAP) ventilation | G184: 1997 | H184: European Respiratory Journal | I184: A 68 yr old woman presented with acute respiratory failure. She was suspected of having a phrenic-diaphragmatic impairment, without evidence of an intrinsic lung disease or generalized neuromuscular disorder, after 3 weeks of prolonged mechanical ventilation. A series of studies, including fluoroscopy, phrenic nerve stimulation test and diaphragmatic electromyography, was performed before the diagnosis of bilateral diaphragmatic paralysis (BDP) was confirmed. The patient was successfully weaned from the conventional mechanical ventilator, and was placed on nasal mask bi-level positive airway pressure (BiPAP) ventilation. A high degree of clinical suspicion of bilateral diaphragmatic paralysis should always be raised in patients suffering respiratory failure without definite predisposing factors. Weaning with noninvasive nasal mask ventilation should be tried first instead of direct tracheostomy. | J184: Asli | K184: Terverifikasi
A185: 181 | B185: S0096 | C185: PubMed | D185: 10.1097/md.0000000000015389 | E185: Liu R, Wang J, Zhao G, Su Z | F185: Negative pressure pulmonary edema after general anesthesia | G185: 2019 | H185: Medicine | I185: Negative pressure pulmonary edema (NPPE) is a dangerous clinical complication and potentially life-threatening emergency without prompt diagnosis and intervention during recovery period after anesthetic extubation. A 25-year-old woman has undergone endoscopic thyroidectomy. After extubation, the patient developed acute respiratory distress with high airway resistance accompanied with wheezing, oxyhemoglobin saturation (SpO 2 ) decreased to 70%. With positive pressure mask ventilation, her condition was stable, SpO 2 99%. However, the patient developed pink frothy sputum with diffuse bilateral rales 30 min later after transported to surgical intensive care unit (SICU). Negative pressure pulmonary edema. The patient was undergone assisted ventilation with continuous positive airway pressure (CPAP) and furosemide 20 mg was given intravenously. Postoperative day (POD) 2 her condition became stable, computed tomography (CT) scan indicated the pulmonary edema disappeared. The patient was discharged 6 days later. No abnormalities were observed during following 4 weeks. Although usually the onset of NPPE is rapid, with individual differences NPPE is still challenging. Increased vigilance in monitoring, diagnosis, and treatment are essential to prevent aggravation and further complication. | J185: Asli | K185: Terverifikasi
A186: 182 | B186: S2199 | C186: PubMed | D186: 10.1159/000064016 | E186: Wiest GH, Harsch IA, Fuchs FS, Kitzbichler S, Bogner K, Brueckl WM, Hahn EG, Ficker JH | F186: Initiation of CPAP Therapy for OSA: Does Prophylactic Humidification during CPAP Pressure Titration Improve Initial Patient Acceptance and Comfort? | G186: 2002 | H186: Respiration | I186: &lt;i&gt;Background:&lt;/i&gt; Heated humidifiers (HH) enable effective treatment of upper airway dryness during nasal continuous positive airway pressure (nCPAP) therapy for obstructive sleep apnoea (OSA), but the role of prophylactic use of HH during the initiation of nCPAP treatment has not been studied so far. &lt;i&gt;Objectives:&lt;/i&gt; The aim of the present study was to investigate whether prophylactic HH during the initiation of CPAP would result in improved initial patient comfort and acceptance. &lt;i&gt;Methods:&lt;/i&gt; In 44 consecutive, previously untreated OSA patients with no history of upper airway dryness, CPAP titration with and without HH was performed on two consecutive nights in a randomised order. The patients were interviewed after each treatment night in order to establish the comfort of the treatment, and, after the second treatment, they were asked which of the two nights they considered more pleasant, and which treatment they would prefer for long-term use. &lt;i&gt;Results:&lt;/i&gt; Following CPAP titration with HH, 32 patients (73%) claimed to have had a better night’s sleep than usual (i.e. without CPAP treatment) compared with 33 patients (75%) saying the same following CPAP treatment without HH. For 21 patients (47.7%) treatment with HH was more pleasant, 23 (52.3%) saw no difference or said that treatment without HH was more pleasant. Nineteen patients (43.2%) gave preference to treatment with HH for long-term use, while 25 patients (56.8%) had no preference or said they would prefer treatment without HH. &lt;i&gt;Conclusions:&lt;/i&gt; The use of HH during the initiation phase of CPAP treatment was associated neither with an initial improvement in comfort nor with greater initial treatment acceptance. | J186: Asli | K186: Terverifikasi
A187: 183 | B187: S0289 | C187: PubMed | D187: 10.1097/01.ccm.0000045563.64187.20 | E187: Kwok H, McCormack J, Cece R, Houtchens J, Hill NS | F187: Controlled trial of oronasal versus nasal mask ventilation in the treatment of acute respiratory failure | G187: 2003 | H187: Critical Care Medicine | I187: Noninvasive positive pressure techniques such as continuous and bilevel positive airway pressure avoid intubation and its attendant complications in selected patients with acute respiratory failure. However, mask intolerance remains a common cause for failure of noninvasive ventilatory techniques. The aim of our study was to assess patient tolerance of oronasal vs. nasal mask ventilation in acute respiratory failure. Randomized, controlled trial. Emergency department or intensive care units at a university hospital. Seventy patients with acute respiratory failure as evidenced by clinical or blood gas criteria. Patients randomly received either a disposable nasal or an oronasal mask (Respironics, Pittsburgh, PA) when they met study criteria. Thirty-five patients were randomized into each arm of the study; most of the patients had acute cardiogenic pulmonary edema (48.6% of the nasal mask group and 42.8% of the facial mask group) or chronic obstructive airway disease (34.3% of the nasal mask group and 31.4% of the facial mask group). Baseline clinical characteristics of the two groups of patients were similar. Heart and respiratory rates and blood gases improved similarly for patients in both mask groups. Rates of intubation were also similar (eight in each group). However, mask intolerance was significantly higher in the nasal than the oronasal mask group (12 vs. 4, respectively, p=.023). Four patients in the nasal (11.4%) and two in the oronasal mask group (5.7%) died later during the hospitalization. The overall success rate tended to be greater in the oronasal (65.7%) than the nasal group (48.6%), but the difference was not statistically significant. Although both masks performed similarly with regard to improving vital signs and gas exchange and avoiding intubation, the nasal mask was less well tolerated than the oronasal mask in patients with acute respiratory failure. | J187: Asli | K187: Terverifikasi
A188: 184 | B188: S1688 | C188: PubMed | D188: 10.1253/jcj.62.553 | E188: Takeda S, Nejima J, Takano T, Nakanishi K, Takayama M, Sakamoto A, Ogawa R | F188: Effect of Nasal Continuous Positive Airway Pressure on Pulmonary Edema Complicating Acute Myocardial Infarction | G188: 1998 | H188: Japanese Circulation Journal | I188: Cardiogenic pulmonary edema is a frequent cause of reparatory failure. We investigated the effects of nasal continuous positive airway pressure (CPAP) in patients with severe pulmonary edema associated with acute myocardial infarction. Twenty-nine consecutive patients were divided into 3 groups: firstly, 7 intubated patients who received mechanical ventilation at study entry comprised the intubation group. The rest of the patients were randomly assigned to either of the following 2 groups: 11 patients who received oxygen plus CPAP delivered by a nasal mask (CPAP group), and 11 patients who received oxygen only via face mask (oxygen group). All patients in the intubation group had cardiogenic shock. Two patients (18%) in the CPAP group and 8 patients (73%) in the oxygen group required mechanical ventilation with endotracheal intubation (p=0.03). The hospital mortality rate in the CPAP group (9%) was significantly lower than the oxygen group (64%, p=0.02). The pulmonary artery wedge pressure and heart rate were significantly lower in the CPAP group than in the oxygen group 24 h after study entry (p<0.05 and p<0.01). The mean pulmonary artery pressure 48 h after study entry was 18+/-5 mmHg in the CPAP group and 25+/-8 mmHg in the oxygen group (p<0.05). The PaO2/FiO2 ratio increased in the intubation group (168+/-69 to 240+/-57, p<0.05) and the CPAP group (137+/-17 to 253+/-67, p<0.01) 24 h after study entry. Arterial plasma endothelin-1 concentrations decreased significantly earlier in the CPAP group than in the oxygen group (p<0.05). In patients without cardiogenic shock, nasal CPAP lead to an early improvement in oxygenation and hemodynamics, and decreased the mortality rate. Early and active respiratory management is recommended in patients with pulmonary edema associated with acute myocardial infarction. | J188: Asli | K188: Terverifikasi
A189: 185 | B189: S0347 | C189: PubMed | D189: 10.3390/jcm10215092 | E189: Yukino M, Nagatomo Y, Goda A, Kohno T, Takei M, Nishihata Y, Saji M, Toyosaki Y, Nakano S, Ikegami Y, Shiraishi Y, Kohsaka S, Adachi T, Yoshikawa T | F189: Association of Non-Invasive Positive Pressure Ventilation with Short-Term Clinical Outcomes in Patients Hospitalized for Acute Decompensated Heart Failure | G189: 2021 | H189: Journal of Clinical Medicine | I189: The real-world evidence has been sparse on the impact of non-invasive positive pressure ventilation (NPPV) on the outcomes in acute decompensated heart failure (ADHF) patients. We aim to explore this issue in the prospective multicenter WET-HF registry. Among 3927 patients (77 (67–84) years, male 60%), the NPPV was used in 775 patients (19.7%). The association of NPPV use with in-hospital outcome and length of hospital stay (LOS) was examined by two methods, propensity score (PS) matching and multivariable analysis with adjustment for PS. In these analyses the NPPV group exhibited a lower endotracheal intubation (ETI) rate and a comparable in-hospital mortality, but longer LOS compared to the non-NPPV group. In the stratified analysis, the NPPV group exhibited a significantly lower ETI rate in patients with ischemic etiology, systolic blood pressure (sBP) &gt; 140 mmHg and the Controlling Nutritional Status (CONUT) score ≤ 3, indicating better nutritional status. On the contrary, NPPV use was associated with longer LOS in patients with non-ischemic etiology, sBP &lt; 100 mmHg and CONUT score &gt; 3. In conclusion, NPPV use was associated with a lower incidence of ETI. Particularly, patients with ischemic etiology, high sBP, and better nutritional status might benefit from NPPV use. | J189: Asli | K189: Terverifikasi
A190: 186 | B190: S2275 | C190: PubMed | D190: 10.1097/01.ccm.0000139694.47326.b6 | E190: Bellone A, Monari A, Cortellaro F, Vettorello M, Arlati S, Coen D | F190: Myocardial infarction rate in acute pulmonary edema: Noninvasive pressure support ventilation versus continuous positive airway pressure | G190: 2004 | H190: Critical Care Medicine | I190: Noninvasive pressure support ventilation (NIPSV) delivered by face mask has proved an effective treatment for patients with acute pulmonary edema. However, an increase in acute myocardial infarction rate has been reported with this ventilation modality. We investigated whether the use of NIPSV increases the incidence of acute myocardial infarction compared with continuous positive airway pressure (CPAP) in patients with acute pulmonary edema. Randomized, prospective, controlled study. Emergency Department, Niguarda Hospital of Milano (Italy). Forty-six patients affected by acute pulmonary edema. The patients received either NIPSV (24 patients) or CPAP (22 patients) through a face mask. Cardiac enzymes (myoglobin, creatine kinase isoenzyme MB, and troponin I) were determined and electrocardiographic and physiologic measurements made over the subsequent 36 hrs. No significant differences were observed in the incidence of acute myocardial infarction in the CPAP group (13.6%) compared with the NIPSV group (8.3%). Both modalities of noninvasive ventilation improved ventilation and vital signs in patients with acute pulmonary edema. Two patients of the NIPSV group (8.3%) and one of the CPAP group (4.5%) required endotracheal intubation because vital signs and arterial blood gases worsened 1 hr after the start of noninvasive ventilation. No significant differences were found in in-hospital mortality rate. NIPSV proved to be equally effective in improving vital signs and ventilation without increasing acute myocardial infarction rate in patients with nonischemic acute pulmonary edema in comparison to CPAP alone. However, because the study lacked statistical power and excluded patients with acute coronary syndromes, caution is still advised when applying NIPSV to the latter subgroup of patients. | J190: Asli | K190: Terverifikasi
... A278: 274 | B278: S0916 | C278: PubMed | D278: 10.1093/ndt/gfaf077 | E278: De Rosa S, Lassola S, Taccone FS, Battaglini D | F278: Chronic lung diseases and kidney disease: pathophysiology and management | G278: 2025 | H278: Nephrology Dialysis Transplantation | I278: Acute kidney injury (AKI) is a critical complication in patients with chronic lung diseases (CLD), particularly during acute exacerbations. This review focuses on the pathophysiological mechanisms linking CLD to AKI and highlights key clinical strategies to mitigate its impact. CLD patients with pre-existing kidney dysfunction face an increased risk of AKI due to impaired gas exchange, systemic inflammation, and neurohormonal activation. Hypoxemia and hypercapnia contribute to kidney hypoperfusion, endothelial dysfunction, and sodium–water imbalances, exacerbating renal injury. Current management strategies prioritize minimizing mechanical ventilation-related damage, optimizing hemodynamics, and preventing AKI progression. A multidisciplinary approach is essential to improving outcomes, emphasizing early identification and targeted interventions for CLD-associated AKI. | J278: Asli | K278: Terverifikasi
A279: 275 | B279: S1534 | C279: PubMed | D279: 10.20944/preprints202609.1542.v1 | E279: Orso D, Meroi F, Brussa A, Ladu M, Spagnolello O, Comisso I, Federici N, Della Rocca G | F279: High-Flow Nasal Cannula in Adult Acute Care: Physiological Mechanisms, Clinical Evidence, and Persistent Misconceptions | G279: 2026 | I279: High-flow nasal cannula (HFNC) oxygen therapy is widely used in emergency, inten-sive care, perioperative, and procedural settings, but it is often conceptually assimilated to non-invasive positive pressure ventilation (NIPPV). This interpretation is physio-logically misleading. HFNC is an open high-flow oxygen system whose main effects derive from dead-space washout, improved stability of inspired oxygen fraction (FiO₂), heated humidification, patient comfort, and only modest flow-dependent positive airway pressure. Its open interface also facilitates eating, drinking, speaking, and se-cretion clearance. Clinical evidence supports HFNC mainly in selected patients with acute hypoxemic respiratory failure, where it may reduce intubation compared with conventional oxygen therapy. However, evidence is more heterogeneous in hypercap-nic respiratory failure, cardiogenic pulmonary edema, immunocompromised patients, obesity, and settings requiring substantial pressure support or ventilatory unloading. NIPPV or continuous positive airway pressure remain preferable when controlled positive pressure, alveolar recruitment, or ventilatory assistance are central to treat-ment. HFNC should therefore be regarded as optimized high-flow oxygen therapy rather than as “non-invasive ventilation through nasal prongs.” Recognizing this dis-tinction may improve patient selection, guide escalation, and avoid overinterpretation of its clinical effects. | J279: Asli | K279: Terverifikasi
A280: 276 | B280: S1406 | C280: PubMed | D280: 10.1111/j.1752-699x.2007.00034.x | E280: Dellborg C, Olofson J, Midgren B, Caro O, Bergman B, Skoogh B, Sullivan M | F280: Impact of home mechanical ventilation on health‐related quality of life in patients with chronic alveolar hypoventilation: a prospective study | G280: 2007 | H280: The Clinical Respiratory Journal | I280: Background: Nocturnal ventilatory support by nasal positive pressure ventilation (NPPV) is an established treatment method in patients with chronic alveolar hypoventilation (CAH). The knowledge about its long‐term effects on health‐related quality of life (HRQL) is limited. Methods: In a prospective, longitudinal, single‐strand study, patients with CAH caused by non‐COPD conditions, consecutively recruited among referral patients in three Swedish university hospital pulmonary departments, were examined at baseline and after 9 months ( n = 35) and 8 years ( n = 11) on NPPV treatment. Both volume pre‐set and pressure pre‐set ventilators were used. Patients completed a battery of condition‐specific and generic HRQL questionnaires at baseline and follow‐up. Spirometry and blood gases were measured. Compliance with treatment, side effects and patient satisfaction were evaluated. Results: After 9 months of NPPV, improvements were seen primarily not only in sleep‐related domains, but also in emotional behaviour, ambulation and sleep/rest functioning as measured with the Sickness Impact Profile (SIP). Improvements in sleep‐related symptoms were related to effectiveness in ventilation, evaluated by morning PaCO 2 , and remained by 8 years. Mental well‐being was stable over time, while emotional distress improved by 8 years. Satisfaction with treatment was high in spite of frequent side effects. Conclusion: NPPV improves HRQL, particularly in condition‐specific areas. Improvements are related to effectiveness in ventilation. Side effects are common, but compliance is good and patient satisfaction is high. Please cite this paper as: Dellborg C, Olofson J, Midgren B, Caro O, Bergman B, Skoogh B‐E and Sullivan M. Impact of home mechanical ventilation on health‐related quality of life in patients with chronic alveolar hypoventilation: a prospective study. The Clinical Respiratory Journal 2008; 2: 26–35. | J280: Asli | K280: Terverifikasi
A281: 277 | B281: S1804 | C281: PubMed | D281: 10.1177/2048872619891075 | E281: Shiraishi Y, Kohsaka S, Katsuki T, Harada K, Miyazaki T, Miyamoto T, Matsushita K, Iida K, Takei M, Yamamoto Y, Shindo A, Kitano D, Nagatomo Y, Jimba T, Yamamoto T, Nagao K, Takayama M, for Tokyo CCU Network Scientific Committee | F281: Benefit and harm of intravenous vasodilators across the clinical profile spectrum in acute cardiogenic pulmonary oedema patients | G281: 2020 | H281: European Heart Journal. Acute Cardiovascular Care | I281: The absence of high quality, large-scale data that indicates definitive mortality benefits does not allow for firm conclusions on the role of intravenous vasodilators in acute heart failure. We aimed to investigate the associations between intravenous vasodilators and clinical outcomes in acute heart failure patients, with a specific focus on patient profiles and type of vasodilators. Data of 26,212 consecutive patients urgently hospitalised for a primary diagnosis of acute heart failure between 2009 and 2015 were extracted from a government-funded multicentre data registration system. Propensity scores were calculated with multiple imputations and 1:1 matching performed between patients with and without vasodilator use. The primary endpoint was inhospital mortality. On direct comparison of the vasodilator and non-vasodilator groups after propensity score matching, there were no significant differences in the inhospital mortality rates (7.5% vs. 8.8%, respectively; P=0.098) or length of intensive/cardiovascular care unit stay and hospital stay between the two groups. However, there was a substantial difference in baseline systolic blood pressure by vasodilator type; favourable impacts of vasodilator use on inhospital mortality were observed among patients who had higher systolic blood pressures and those who had no atrial fibrillation on admission. Furthermore, when compared to nitrates, the use of carperitide (natriuretic peptide agent) was significantly associated with worse outcomes, especially in patients with intermediate systolic blood pressures. In acute heart failure patients, vasodilator use was not universally associated with improved inhospital outcomes; rather, its effect depended on individual clinical presentation: patients with higher systolic blood pressure and no atrial fibrillation seemed to benefit maximally from vasodilators. UMIN-CTR identifier, UMIN000013128 | J281: Asli | K281: Terverifikasi
A282: 278 | B282: S1854 | C282: PubMed | D282: 10.1016/s1441-2772(23)00131-x | E282: Duke GJ, Bersten AD | F282: Non-Invasive Ventilation for Adult Acute Respiratory Failure. Part I | G282: 1999 | H282: Critical Care and Resuscitation | I282: Objective To discuss the clinical indications and complications of non-invasive ventilation. Data sources A review of articles published in peer-reviewed journals from 1966 to 1998 and identified through a MEDLINE search on non-invasive ventilation. Summary of review Non-invasive ventilation (NIV) has been used in patients with respiratory failure caused by cardiogenic pulmonary oedema, acute respiratory distress syndrome, acute asthma and chronic obstructive pulmonary disease. However, in patients with acute respiratory failure, it appears that acute cardiogenic pulmonary oedema and acute respiratory failure associated with Pneumocystis carinii pneumonia are the only disorders in which significant benefits have been associated with the use of the NIV mode of CPAP. The potential clinical benefit of CPAP in acute asthma and blunt chest trauma remains unclear. Pressure support ventilation is beneficial in patients with hypercapnic acute respiratory failure (ARF) secondary to respiratory muscle insufficiency, high inspiratory work loads, or reduced alveolar ventilation. It appears also to be associated with an improved outcome in COPD patients with hypercapnic ARF. Conclusions Non-invasive ventilation using the modes of CPAP, PSV, BiPAP and NIPPV should be considered in patients with respiratory disorders who remain in acute respiratory failure despite conventional therapy, before considering invasive mechanical ventilation. | J282: Asli | K282: Terverifikasi
A283: 279 | B283: S0281 | C283: PubMed | D283: 10.1016/s1388-9842(02)00205-2 | E283: van Kraaij DJW, Jansen RWMM, Sweep FCGJ, Hoefnagels WHL | F283: Neurohormonal Effects of Furosemide Withdrawal in Elderly Heart Failure Patients with Normal Systolic Function | G283: 2003 | H283: European Journal of Heart Failure | I283: In heart failure patients, diuretics cause renin–angiotensin–aldosterone system (RAS) activation, which may lead to increased morbidity and mortality despite short-term symptomatic improvement. To determine changes in RAS activation and clinical correlates following furosemide withdrawal in elderly heart failure patients without left ventricular systolic dysfunction. We performed clinical assessments and laboratory determinations of aldosterone, plasma renin activity (PRA), atrial natriuretic peptide (ANP), norepinephrine, and endothelin in 29 heart failure patients [aged 75.1±0.7 (mean±S.E.M.) years], before, 1 and 3 months after placebo-controlled furosemide withdrawal. Recurrent congestion occurred in 2 of 19 patients withdrawn, and in 1 of 10 patients continuing on furosemide. Three months after withdrawal, PRA had decreased −1.61±0.71 nmol/l/h (P&amp;lt;0.05). Decreases in aldosterone levels did not reach significance (−0.17±0.38 nmol/l). The decreases in PRA after withdrawal correlated with decreases in systolic (rs=0.61, P=0.020) and diastolic blood pressure (rs=0.80, P=0.01). Successful withdrawal was associated with increases in norepinephrine (+0.58±0.22 nmol/l) and ANP (+3.5±1.3 pmol/l) (P&amp;lt;0.05) after 1 month, but these changes did not persist after 3 months. Endothelin levels did not change in both groups. Successful furosemide withdrawal in elderly heart failure patients causes persistent decreases in RAS activation. | J283: Asli | K283: Terverifikasi
A284: 280 | B284: S1927 | C284: PubMed | D284: 10.1183/09031936.02.00288402 | E284: Herold CJ | F284: Spiral computed tomography of pulmonary embolism | G284: 2002 | H284: European Respiratory Journal | I284: Within the last several years, spiral computed tomography angiography (SCTA) of the pulmonary arteries has emerged as a noninvasive angiographic modality for the evaluation of patients with suspected pulmonary embolism (PE). SCTA is based on continuous computed tomography (CT) data acquisition during patient transport through the rotating X‐ray tube and detector system, where scanning is performed in the time period in which the injected contrast material passes through the pulmonary arteries. Single detector spiral CT has a sensitivity of ∼85–90% and a specificity between 88–95%. Sensitivity and specificity are very likely to increase with the use of multidetector spiral CT scanners that allow scanning of large lung volumes with a scan collimation as narrow as 1 mm. Currently, SCTA is most commonly used as a primary imaging method in patients with suspected PE, and as a second-line method in cases with inconclusive ventilation/perfusion scintigraphy results. SCTA has proven to be cost-effective, especially in combination with ultrasound of the lower extremities. Limitations of the method include a decreased sensitivity for the detection of small isolated clots in the peripheral pulmonary arterial bed, and a potentially reduced image quality in patients with coexistent cardiopulmonary disorders. Despite these limitations, several studies have now documented that, in patients with suspected pulmonary embolism, it is safe to withhold anticoagulation therapy if a spiral computed tomography exam of the pulmonary arteries is negative and no lower extremity venous thrombosis is present. In the future, multislice computed tomography scanning of the pulmonary arteries with multiplanar reformation and one-stop shopping, i.e. scanning of the pulmonary arteries and the lower extremity veins in a single session, will further enhance the role of computed tomography angiography in the examination of patients with suspected pulmonary embolism. | J284: Asli | K284: Terverifikasi
A285: 281 | B285: S2282 | C285: PubMed | D285: 10.1046/j.1365-2796.2001.00786.x | E285: Holmer SR, Hengstenberg C, Mayer B, Engel S, Löwel H, Riegger GAJ, Schunkert H | F285: Marked suppression of renin levels by β‐receptor blocker in patients treated with standard heart failure therapy: a potential mechanism of benefit from β‐blockade | G285: 2001 | H285: Journal of Internal Medicine | I285: Abstract. Holmer SR, Hengstenberg C, Mayer B, Engel S, Löwel H, Riegger GAJ, Schunkert H (University of Regensburg, Regensburg, and GSF‐Institut für Epidemiologie, Munich‐Neuherberg, Germany). Marked suppression of renin levels by β‐receptor blocker in patients treated with standard heart failure therapy: a potential mechanism of benefit from β‐blockade. J Intern Med 2001; 249: 167–172. Objectives. Recent trials demonstrated beneficial effects of β‐blockers in combination with standard heart failure medication. The mechanisms underlying this benefit are incompletely understood. We hypothesized that β‐blockers may augment the inhibition of the renin–angiotensin system in patients with left ventricular (LV) dysfunction treated with angiotensin‐converting enzyme (ACE) inhibitors and/or diuretics by prevention of renin upregulation that occurs in such patients. Design. We examined plasma renin levels (direct radioimmunometric assay) in 312 men with previous myocardial infarction (MI) and echocardiographic LV dysfunction. Patients took medication according to their physicians’ prescriptions: antiplatelet agents alone ( n =62) or in combination with ACE inhibitors, diuretics or β‐blockers ( n =250). Results. Plasma renin levels were elevated in patients taking ACE inhibitors or diuretics and ACE inhibitors plus diuretics (adjusted means from multiple regression analysis were 28.5 mU L −1 [95% CI=20.6–39.5] and 73.7 mU L −1 [95% CI = 49.9– 109.9], respectively) compared with patients on antiplatelets alone (16.1 mU L −1 , 95% CI = 13.5–19.3, P &lt; 0.05 each). The combinations of β‐blockers with ACE inhibitors or diuretics and β‐blockers with ACE inhibitors plus diuretics were related to markedly suppressed plasma renin levels (adjusted means 16.4 [13.1–20.6] and 32.1 [23.3–44.3]) as compared with respective patient groups without β‐blockers ( P &lt; 0.01 each). Conclusions. Concomitant β‐blocker treatment can prevent the reactive renin stimulation and potentially the escape from effective inhibition of the renin–angiotensin system in patients with LV dysfunction after MI treated with ACE‐inhibitors and/or diuretics. | J285: Asli | K285: Terverifikasi
A286: 282 | B286: S0699 | C286: PubMed | D286: 10.1002/ajum.70053 | E286: Aldawood A, Al Doaibel K | F286: Contrast‐Induced Non‐Cardiogenic Pulmonary Oedema Detected by Lung Ultrasound: A Case Report | G286: 2026 | H286: Australasian Journal of Ultrasound in Medicine | I286: Pulmonary oedema is characterised by fluid accumulation within the alveoli, impairing gas exchange and causing respiratory distress. While cardiogenic pulmonary oedema is common, non‐cardiogenic causes are less frequent and typically result from increased capillary permeability. Contrast‐induced non‐cardiogenic pulmonary oedema (NCPE) is rare but clinically significant. We report a case of NCPE following iodinated contrast administration during breast imaging. Point‐of‐Care Lung ultrasound (LUS) detected early interstitial fluid through diffuse bilateral B‐lines, which were not evident on chest radiography. This facilitated prompt diagnosis and guided timely treatment with non‐invasive ventilation and intravenous furosemide. This case highlights contrast‐induced NCPE as a rare adverse event and demonstrates the role of bedside LUS as a rapid, non‐invasive diagnostic modality. Early detection supported timely intervention and contributed to rapid clinical improvement. Wider integration of LUS in an acute care setting may enhance diagnostic accuracy and improve patient outcomes. | J286: Asli | K286: Terverifikasi
A287: 283 | B287: S2110 | C287: PubMed | D287: 10.1016/j.suc.2021.09.012 | E287: Popowicz P, Leonard K | F287: Noninvasive Ventilation and Oxygenation Strategies | G287: 2022 | H287: Surgical Clinics of North America | I287: Noninvasive ventilation (NIV) provides respiratory support without the use of invasive ventilation with techniques that do not bypass the upper airway. NIV is particularly attractive given its associated reduced risk of complications associated with intubation. Available NIV modes include nasal cannula, simple mask, nonrebreather, high flow nasal cannula, continuous positive airway pressure (CPAP), and bilevel positive airway pressure. Acute exacerbation of COPD, cardiogenic pulmonary edema, and COVID-19 are conditions for which NIV has shown to be beneficial, whereas there is no consensus among the use of NIV in trauma patients and ARDS. | J287: Asli | K287: Terverifikasi
A288: 284 | B288: S1703 | C288: PubMed | D288: 10.1063/1.1562051 | E288: Echeverrı́a JC, Woolfson MS, Crowe JA, Hayes-Gill BR, Croaker GDH, Vyas H | F288: Interpretation of heart rate variability via detrended fluctuation analysis and αβ filter | G288: 2003 | H288: Chaos: An Interdisciplinary Journal of Nonlinear Science | I288: Detrended fluctuation analysis (DFA), suitable for the analysis of nonstationary time series, has confirmed the existence of persistent long-range correlations in healthy heart rate variability data. In this paper, we present the incorporation of the αβ filter to DFA to determine patterns in the power-law behavior that can be found in these correlations. Well-known simulated scenarios and real data involving normal and pathological circumstances were used to evaluate this process. The results presented here suggest the existence of evolving patterns, not always following a uniform power-law behavior, that cannot be described by scaling exponents estimated using a linear procedure over two predefined ranges. Instead, the power law is observed to have a continuous variation with segment length. We also show that the study of these patterns, avoiding initial assumptions about the nature of the data, may confer advantages to DFA by revealing more clearly abnormal physiological conditions detected in congestive heart failure patients related to the existence of dominant characteristic scales. | J288: Asli | K288: Terverifikasi
A289: 285 | B289: S1504 | C289: PubMed | D289: 10.3390/biomedicines13081844 | E289: Scicchitano P, Cinelli A, Citarelli G, Livrieri A, Campanella C, De Palo M, Caldarola P, Ciccone MM, Massari F | F289: The Prognostic Value of Non-Invasive Ventilation in Patients with Acute Heart Failure | G289: 2025 | H289: Biomedicines | I289: Objectives: Patients with acute heart failure (AHF) often receive initial non-invasive ventilation (NIV). This study aimed to evaluate the prognostic role of NIV in patients hospitalized for AHF. Methods: This was a retrospective cohort study. We enrolled patients admitted to our cardiac intensive care unit with a diagnosis of AHF. Anthropometric, clinical, pharmacological, and instrumental assessments were collected. Both in-hospital and 180-day post-discharge mortality were evaluated. Results: Among 200 patients (mean age 81 ± 9 years; 52% male), NIV was applied in 80 cases (40%). These patients had more severe NYHA functional class, a higher prevalence of de novo AHF, required higher diuretic doses, and had longer hospital stays. In multivariate analysis, NIV remained significantly associated with length of stay (LOS) (r = 0.26; p = 0.0004). In-hospital mortality was 5% overall and significantly higher in the NIV group compared to non-NIV patients (10% vs. 1.6%, p &lt; 0.001). At 180 days, mortality was also significantly higher in the NIV group [hazard ratio (HR) 1.84; 95% confidence interval (CI): 1.18–2.85; p = 0.006]. After adjusting for age, BNP, CRP, arterial blood gas parameters, renal function, and LVEF, NIV remained an independent predictor of 180-day mortality (HR 1.61; 95% CI: 1.01–2.54; p = 0.04). Conclusions: Patients with AHF who required NIV exhibited more severe disease and longer hospital stays. NIV use was independently associated with both in-hospital and post-discharge mortality, suggesting its potential role as a prognostic marker in AHF. | J289: Asli | K289: Terverifikasi
A290: 286 | B290: S0027 | C290: PubMed | D290: 10.21037/jtd-23-732 | E290: Rittayamai N, Pravarnpat C, Srilam W, Bunyarid S, Chierakul N | F290: Safety and efficacy of noninvasive ventilation for acute respiratory failure in general medical ward: a prospective cohort study | G290: 2023 | H290: Journal of Thoracic Disease | I290: Background Noninvasive ventilation (NIV) is recommended for use in patients with acute respiratory failure of various etiologies. However, we do not know whether the use of NIV in general medical wards is safe and effective. This study aimed to evaluate the safety and efficacy of using NIV and factors associated with NIV failure in general medical wards. Methods A prospective cohort study was conducted in general medical wards of the University Hospital. Adult patients with acute respiratory failure treated with NIV were enrolled. The subjects were managed by a multidisciplinary care team that was well trained in the NIV device. The primary outcome was the rate of NIV failure at 48 hours. Secondary outcomes included hospital mortality and factors associated with NIV failure. Results A total of 86 patients were enrolled. The mean age was 70±17 years old. The Acute Physiology and Chronic Health Evaluation (APACHE) III and the Sequential Organ Failure Assessment (SOFA) scores were 56±17 and 4±3, respectively. The most common indication of NIV use was cardiogenic pulmonary edema (34.9%). The rate of NIV failure at 48 hours and hospital mortality were 20.9% and 12.8%, respectively. The SOFA score was associated with failure of NIV at 48 hours [odds ratio (OR) 1.48, 95% confidence interval (CI): 1.16-1.89; P=0.002]. Conclusions NIV was safe and effective on general medical wards. Cardiogenic pulmonary edema was the most common indication for the application of NIV. The SOFA score was associated with the failure of NIV at 48 hours. | J290: Asli | K290: Terverifikasi
A291: 287 | B291: S2366 | C291: PubMed | D291: 10.1177/1479972307080697 | E291: Toussaint M, Chatwin M, Soudon P | F291: Review Article: Mechanical ventilation in Duchenne patients with chronic respiratory insufficiency: clinical implications of 20 years published experience | G291: 2007 | H291: Chronic Respiratory Disease | I291: Chronic respiratory insufficiency is inevitable in the course of disease progression in patients with Duchenne muscular dystrophy (DMD). Without mechanical ventilation (MV), morbidity and mortality are highly likely towards the end of the second decade of life. The present review reports evidence and clinical implications regarding DMD patients treated with MV. There is no doubt that nocturnal hypercapnia precedes daytime hypercapnia. Historical comparisons have provided evidence that non-invasive intermittent positive pressure ventilation (NIPPV) at night is effective and improves quality of life and survival by 5—10 years. By contrast, the optimal criteria and timing for initiation of NIPPV are inconsistent. A recent randomized study however demonstrated the benefits of commencing NIPPV as soon as nocturnal hypoventilation is detected (Ward S, et al., Randomised controlled trial of non-invasive ventilation (NIV) for nocturnal hypoventilation in neuromuscular and chest wall disease patients with daytime normocapnia. Thorax 2005; 60: 1019—24). The respective role of the three hypotheses of the indirect action of nocturnal NIPPV on daytime blood gases may be complimentary; the main improvement may be due to improved ventilatory response to CO2. The ultimate time to offer full time ventilation with the most advantageous interface is lacking in evidence. Full time NIV is possible with a combination of a nasal mask during the night and a mouthpiece during the day, however tracheostomy may be provided when mechanical techniques of cough-assistance are useless to treat chronic cough insufficiency. Chronic Respiratory Disease 2007; 4: 167—177 | J291: Asli | K291: Terverifikasi
... A689: 685 | B689: S1595 | C689: PubMed | D689: 10.1111/j.1651-2227.2011.02543.x | E689: Bohlin K | F689: RDS – CPAP or surfactant or both | G689: 2012 | H689: Acta Paediatrica | I689: There is mounting evidence that early continuous positive airway pressure (CPAP) from birth is feasible and safe even in very preterm infants. However, many infants will develop respiratory distress syndrome (RDS) and require surfactant treatment. Combining a non‐invasive ventilation approach with a strategy for surfactant administration is important, but questions remain about the optimal timing, mode of delivery and the value of predictive tests for surfactant deficiency. Conclusion: Early CPAP in very preterm infants is as safe as routine intubation in the delivery room. However, a strategy for surfactant administration should be part of a non‐invasive ventilation approach for those infants at risk of developing significant RDS.’ | J689: Asli | K689: Terverifikasi
A690: 686 | B690: S0431 | C690: PubMed | D690: 10.1101/2023.03.25.23287602 | E690: Perel N, Amsalem I, Gilad O, Hitter R, Maller T, Asher E, Harari E, Marmor D, Carasso S, Dvir D, Glikson M, Shuvy M | F690: Urgent Transcatheter Edge-to-Edge Repair for Severe Mitral Regurgitation with Flail Leaflet in Critically Ill Patients | G690: 2023 | I690: Degenerative mitral valve disease (DMR) is a common valvular disorder, and flail leaflet due to ruptured chordae represents an extreme variation of this pathology. Ruptured chordae can present as acute heart failure which requires urgent intervention. Mitral valve surgery is the preferred mode of intervention; however, some patients represent as a significant surgical risk and are often deemed to be inoperable. We aim to characterize patients with ruptured chordae undergoing urgent transcatheter edge-to-edge repair (TEER), and to analyze their clinical and echocardiographic outcomes. At a referral center for several hospitals across Israel, we screened all patients who underwent TEER. We included patients with DMR with flail leaflet due to ruptured chordae, and categorized them into elective and critically ill groups. We evaluated the echocardiographic, hemodynamic and clinical outcomes of these patients. The cohort included 49 patients with DMR due to ruptured chordae and flail leaflet, who underwent TEER. Seventeen patients (35%) underwent urgent intervention and 32 patients (65%) underwent an elective procedure. In the urgent group, the average age of the patient was 80.3, with 41.8% being female. Fourteen (82%) received noninvasive ventilation, while three patients (18%) required invasive mechanical ventilation. One patient died due to tamponade, while the other 16 patients all had successful reduction of ≥2 in the MR grade. Left atrial V wave decreased from 41.6 mmHg to 17.9 mmHg (p&lt;0.001), and pulmonic vein flow pattern changed from reversal (68.8%) to a systolic dominant flow in all patients (p=0.001). After the procedure, 78.5% of patients were in New York Heart Association (NYHA) class I or II (p&lt;0.001). There was no significant difference in the overall mortality between the urgent and elective groups, with similar survival rates of 6 months for each group. TEER can be safe and feasible with favorable hemodynamic, echocardiographic and clinical outcomes in patients undergoing urgent intervention for flail mitral valve disease. Mitral transcatheter edge-to-edge repair (TEER) is a proven therapy for patients with chronic mitral regurgitation, however data on patients with acute mitral regurgitation limited. This article focuses on acute TEER intervention and provides further information on the safety, feasibility and effectiveness of TEER in critically ill patients due to flail leaflet. The clinical finding supports the role of acute TEER intervention in acutely ill patients with acute mitral regurgitation due to ruptured chordae and flail leaflet. | J690: Asli | K690: Terverifikasi
A691: 687 | B691: S2067 | C691: PubMed | D691: 10.1034/j.1399-0039.2001.057002151.x | E691: Bijlsma FJ, Bruggink AH, Hartman M, Gmelig‐Meyling FHJ, Tilanus MGJ, De Jonge N, De Weger RA | F691: No association between IL‐10 promoter gene polymorphism and heart failure or rejection following cardiac transplantation | G691: 2001 | H691: Tissue Antigens | I691: Abstract: Expression of interleukin (IL)‐10 influences the frequency of rejection events after organ transplantation. Therefore, 70 heart transplant patients were genotyped for three single nucleotide polymorphisms and a microsatellite polymorphism in the promotor region of the IL‐10 gene. The promoter region was amplified by polymerase chain reaction and genotyped by a colorometric oligo ligation assay and gene scan analysis, respectively. Patient groups consisted of patients suffering from dilated cardiomyopathy or ischaemic heart disease. Cardiac donors served as control group. No correlation was found between genotypes and heart failure or rejection after heart transplantation. This may indicate that in heart transplantation, the total balance of cytokine production is more important for post‐transplant rejection activities than the levels of IL‐10 as such. | J691: Asli | K691: Terverifikasi
A692: 688 | B692: S1197 | C692: PubMed | D692: 10.1146/annurev.med.52.1.221 | E692: Weinacker AB, Vaszar LT | F692: Acute Respiratory Distress Syndrome: Physiology and New Management Strategies | G692: 2001 | H692: Annual Review of Medicine | I692: ▪ Abstract The acute respiratory distress syndrome (ARDS) has been recognized for more than three decades as a cause of respiratory failure in patients with a variety of illnesses. Clinically, it is characterized by pulmonary edema, refractory hypoxemia, diffuse pulmonary infiltrates, and altered lung compliance. Pathologically, it is distinguished by infiltration of the lungs with inflammatory cells, interstitial and alveolar edema, hyaline membrane formation, and ultimately fibrosis. Although we have learned much about the pathophysiology of this inflammatory syndrome since its earliest descriptions, ARDS continues to claim the lives of 40%–70% of its victims. Many treatment strategies have been used to prevent or treat ARDS, but thus far the most encouraging strategy to prevent lung injury and improve survival is mechanical ventilation with low tidal volumes and high levels of positive end-expiratory pressure. | J692: Asli | K692: Terverifikasi
A693: 689 | B693: S1743 | C693: PubMed | D693: 10.1055/s-0029-1237100 | E693: Sellmann T, Meyer–Treschan T, Marx F, Meyer J | F693: Kasuistik interaktiv – Respiratorische Insuffizienz bei 102–Jährigem: Intubation vs. NIV in der Präklinik | G693: 2009 | H693: AINS - Anästhesiologie · Intensivmedizin · Notfallmedizin · Schmerztherapie | I693: Guidelines for the therapy of cardiogenic pulmonary edema or acute exacerbation of COPD imply the use of noninvasive ventilation (NIV). Clinical studies show a decrease in intubation frequency, mortality and length of stay with inhospital NIV. First prehospital reports show a safe and feasible use of NIV in this setting. We report the case of a 102-year old patient who was successfully treated with preclinical NIV. | J693: Asli | K693: Terverifikasi
A694: 690 | B694: S1660 | C694: PubMed | D694: 10.1046/j.1365-2796.1998.00291.x | E694: Rossinen, Partanen, Stenius‐Aarniala, Nieminen | F694: Salbutamol inhalation has no effect on myocardial ischaemia, arrhythmias and heart‐rate variability in patients with coronary artery disease plus asthma or chronic obstructive pulmonary disease | G694: 1998 | H694: Journal of Internal Medicine | I694: Rossinen J, Partanen J, Stenius‐Aarniala B, Nieminen MS (Helsinki University Central Hospital, Helsinki, Finland). Salbutamol inhalation has no effect on myocardial ischaemia, arrhythmias and heart‐rate variability in patients with coronary artery disease plus asthma or chronic obstructive pulmonary disease. J Intern Med 1998; 243 : 361–66. Inhaled beta‐2 agonists raise heart rate, systolic blood pressure and contractility, all of which cause an increase in oxygen consumption of the heart. We performed a study on the influ‐ ence of inhaled salbutamol on myocardial ischa‐emia, rhythm, and heart rate variability as assessed by Holter monitoring of 24 patients with coronary artery disease (CAD) and clinically stable asthma or chronic obstructive pulmonary disease (COPD). In hospital the patients received 0.2 mg (hour 1), 0.4 mg (hour 6), 0.8 mg (hour 13) of salbutamol with a metered‐dose inhaler and a spacer, and 5 mg (hour 25) with a nebulizer; symptoms, peak expiratory flow ( PEF ), 30‐h Holter monitoring, and blood pressure (BP) were recorded. The study parameters were compared for the hour preceding and following each dose of salbutamol. No cardiac symptoms were associated with salbutamol inhalation. PEF increased after all doses ( P &lt; 0.005). A dose of 0.2 mg salbutamol induced no changes in heart rate, whereas dose of 0.4 mg increased heart rate from a mean of 75 ± 13 to 79 ± 14 beats min −1 ( P &lt; 0.005), and a dose of 0.8 mg from 76 ± 14 to 78 ± 15 beats min −1 ( P &lt; 0.05). No changes in systolic BP appeared after any dose of salbutamol. The diastolic BP was lowered after 0.8 mg of salbutamol from 86 ± 12 to 82 ± 10 mmHg ( P &lt; 0.05). The 5 mg of nebulized drug provoked no significant changes in heart rate or BP. Myocardial ischaemia, heart rate variability and ventricular arrhythmias remained unaltered with all doses. The commonly used doses of inhaled or nebulized salbutamol induced no acute myocardial ischaemia, arrhythmias or changes in heart rate variability in patients with CAD and clinically stable asthma or COPD. | J694: Asli | K694: Terverifikasi
A695: 691 | B695: S1856 | C695: PubMed | D695: 10.1111/j.1365-2044.2007.05190.x | E695: Munckton K, Ho KM, Dobb GJ, Das‐Gupta M, Webb SA | F695: The pressure effects of facemasks during noninvasive ventilation: a volunteer study | G695: 2007 | H695: Anaesthesia | I695: Noninvasive ventilation by facemask is commonly used for patients with respiratory failure. We evaluated the pressure exerted by two types of facemask on the faces of 12 healthy volunteers while they were being given different levels of continuous or bi‐level positive airway pressure ventilation. The mean (SD) pressure recorded on the bridge of the nose was much higher than that on the cheek (nose: 65.8 (21.2) vs cheek 15.4 (7.2) mmHg, p &lt; 0.0001). Progressive tightening of the harness and increasing of the volume of air in the facemask cushions increased the pressure on the bridge of the nose, and the effect of these two factors was additive. Some commercially available facemasks can produce substantial pressure on the bridge of the nose and this explains why pressure complications on the bridge of the nose are common during noninvasive ventilation. | J695: Asli | K695: Terverifikasi
A696: 692 | B696: S0452 | C696: PubMed | D696: 10.1002/14651858.cd012466.pub2 | E696: Lunney M, Ruospo M, Natale P, Quinn RR, Ronksley PE, Konstantinidis I, Palmer SC, Tonelli M, Strippoli GF, Ravani P | F696: Pharmacological interventions for heart failure in people with chronic kidney disease | G696: 2020 | H696: Cochrane Database of Systematic Reviews | I696: Background Approximately half of people with heart failure have chronic kidney disease (CKD). Pharmacological interventions for heart failure in people with CKD have the potential to reduce death (any cause) or hospitalisations for decompensated heart failure. However, these interventions are of uncertain benefit and may increase the risk of harm, such as hypotension and electrolyte abnormalities, in those with CKD. Objectives This review aims to look at the benefits and harms of pharmacological interventions for HF (i.e., antihypertensive agents, inotropes, and agents that may improve the heart performance indirectly) in people with HF and CKD. Search methods We searched the Cochrane Kidney and Transplant Register of Studies through 12 September 2019 in consultation with an Information Specialist and using search terms relevant to this review. Studies in the Register are identified through searches of CENTRAL, MEDLINE, and EMBASE, conference proceedings, the International Clinical Trials Register (ICTRP) Search Portal and ClinicalTrials.gov. Selection criteria We included randomised controlled trials of any pharmacological intervention for acute or chronic heart failure, among people of any age with chronic kidney disease of at least three months duration. Data collection and analysis Two authors independently screened the records to identify eligible studies and extracted data on the following dichotomous outcomes: death, hospitalisations, worsening heart failure, worsening kidney function, hyperkalaemia, and hypotension. We used random effects meta-analysis to estimate treatment effects, which we expressed as a risk ratio (RR) with 95% confidence intervals (CI). We assessed the risk of bias using the Cochrane tool. We applied the GRADE methodology to rate the certainty of evidence. Main results One hundred and twelve studies met our selection criteria: 15 were studies of adults with CKD; 16 studies were conducted in the general population but provided subgroup data for people with CKD; and 81 studies included individuals with CKD, however, data for this subgroup were not provided. The risk of bias in all 112 studies was frequently high or unclear. Of the 31 studies (23,762 participants) with data on CKD patients, follow-up ranged from three months to five years, and study size ranged from 16 to 2916 participants. In total, 26 studies (19,612 participants) reported disaggregated and extractable data on at least one outcome of interest for our review and were included in our meta-analyses. In acute heart failure, the effects of adenosine A1-receptor antagonists, dopamine, nesiritide, or serelaxin on death, hospitalisations, worsening heart failure or kidney function, hyperkalaemia, hypotension or quality of life were uncertain due to sparse data or were not reported. In chronic heart failure, the effects of angiotensin-converting enzyme inhibitors (ACEi) or angiotensin receptor blockers (ARB) (4 studies, 5003 participants: RR 0.85, 95% CI 0.70 to 1.02; I 2 = 78%; low certainty evidence), aldosterone antagonists (2 studies, 34 participants: RR 0.61 95% CI 0.06 to 6.59; very low certainty evidence), and vasopressin receptor antagonists (RR 1.26, 95% CI 0.55 to 2.89; 2 studies, 1840 participants; low certainty evidence) on death (any cause) were uncertain. Treatment with beta-blockers may reduce the risk of death (any cause) (4 studies, 3136 participants: RR 0.69, 95% CI 0.60 to 0.79; I 2 = 0%; moderate certainty evidence). Treatment with ACEi or ARB (2 studies, 1368 participants: RR 0.90, 95% CI 0.43 to 1.90; I 2 = 97%; very low certainty evidence) had uncertain effects on hospitalisation for heart failure, as treatment estimates were consistent with either benefit or harm. Treatment with beta-blockers may decrease hospitalisation for heart failure (3 studies, 2287 participants: RR 0.67, 95% CI 0.43 to 1.05; I 2 = 87%; low certainty evidence). Aldosterone antagonists may increase the risk of hyperkalaemia compared to placebo or no treatment (3 studies, 826 participants: RR 2.91, 95% CI 2.03 to 4.17; I 2 = 0%; low certainty evidence). Renin inhibitors had uncertain risks of hyperkalaemia (2 studies, 142 participants: RR 0.86, 95% CI 0.49 to 1.49; I 2 = 0%; very low certainty). We were unable to estimate whether treatment with sinus node inhibitors affects the risk of hyperkalaemia, as there were few studies and meta-analysis was not possible. Hyperkalaemia was not reported for the CKD subgroup in studies investigating other therapies. The effects of ACEi or ARB, or aldosterone antagonists on worsening heart failure or kidney function, hypotension, or quality of life were uncertain due to sparse data or were not reported. Effects of anti-arrhythmic agents, digoxin, phosphodiesterase inhibitors, renin inhibitors, sinus node inhibitors, vasodilators, and vasopressin receptor antagonists were very uncertain due to the paucity of studies. Authors' conclusions The effects of pharmacological interventions for heart failure in people with CKD are uncertain and there is insufficient evidence to inform clinical practice. Study data for treatment outcomes in patients with heart failure and CKD are sparse despite the potential impact of kidney impairment on the benefits and harms of treatment. Future research aimed at analysing existing data in general population HF studies to explore the effect in subgroups of patients with CKD, considering stage of disease, may yield valuable insights for the management of people with HF and CKD. | J696: Asli | K696: Terverifikasi
A697: 693 | B697: S1316 | C697: PubMed | D697: 10.1161/circheartfailure.108.820183 | E697: Gray A, Goodacre S, Nicholl J, Masson M, Sampson F, Elliott M, Crane S, Newby DE | F697: The Development of a Simple Risk Score to Predict Early Outcome in Severe Acute Acidotic Cardiogenic Pulmonary Edema | G697: 2010 | H697: Circulation: Heart Failure | I697: Background— Acute cardiogenic pulmonary edema is a common medical emergency with high early mortality. Initial clinical assessment would benefit from accurate mortality prediction. We aimed to develop a simple clinical score based on presenting characteristics that would predict 7-day mortality in patients with acute cardiogenic pulmonary edema. Methods and Results— We used data from patients recruited to the 3CPO trial (a pragmatic multicenter trial comparing continuous positive airway pressure, noninvasive positive pressure ventilation, and standard oxygen therapy in emergency department patients with acute cardiogenic pulmonary edema) to investigate the association between baseline characteristics and 7-day mortality. Factors associated with mortality ( P &lt;0.1) were entered into a multivariable model. Independent predictors of mortality from the multivariable model ( P &lt;0.05) were assigned integer weights based on their coefficients and incorporated into a risk score. The discriminant ability of the score was tested by receiver operator characteristic analysis. Data from 1069 patients (78±10 years; 43% men; 7-day mortality, 9.6%) were analyzed. Multivariable analysis identified age ( P =0.003), systolic blood pressure ( P &lt;0.001), and Glasgow Coma Scale motor component dichotomized and simplified to the ability to obey commands or not ( P =0.02) as the only independent predictors of 7-day mortality. These were weighted and used to develop a risk score ranging from 0 (7-day mortality, 1.9%; 95% CI, 0.8 to 4.5) to 7 (7-day mortality, 100%; 95% CI, 34.2 to 100). Receiver operator characteristic analysis demonstrated good risk prediction with a c-statistic of 0.794 (95% CI, 0.745 to 0.843). A simplified 3-point score with no weighting had a c-statistic of 0.754 (95% CI, 0.701 to 0.807). Conclusions— A simple clinical score based on age, systolic blood pressure, and the ability to obey commands predicts early mortality in patients with acute cardiogenic pulmonary edema. Clinical Trial Registration— clinicaltrials.gov Identifier: ISRCTN077448447. | J697: Asli | K697: Terverifikasi
A698: 694 | B698: S0061 | C698: PubMed | D698: 10.1177/1753495x17708949 | E698: Daly A, Robertson A, Bobek G, Middleton S, Sullivan C, Hennessy A | F698: Sleep disordered breathing controlled by CPAP and sFlt-1 in a pregnant patient with chronic hypertension: Case report and literature review | G698: 2017 | H698: Obstetric Medicine | I698: There is recent interest exploring the possible impact of sleep disordered breathing on the mechanisms of preeclampsia. A biomarker of preeclampsia, soluble fms-like tyrosine kinase-1, has come to prominence in recent years. The aim of this study was to investigate the relationship between continuous positive airway pressure treatment, sleep disordered breathing and soluble fms-like tyrosine kinase-1 concentrations during pregnancy. A 38-year-old G1P0 presented at 20 + 5 weeks. She had a history of chronic hypertension. Sleep studies revealed she had sleep disordered breathing with an AHI of 7.3/h. She was commenced on continuous positive airway pressure. Soluble fms-like tyrosine kinase-1 concentrations and blood pressure recordings were taken at various points during her pregnancy. She did not develop preeclampsia or require an escalation in her antihypertensives. Soluble fms-like tyrosine kinase-1 concentrations rose 16% from a low baseline. She remained compliant with her continuous positive airway pressure. She progressed to birth a well, live, term baby. Continuous positive airway pressure treatment controlled sleep disordered breathing in a high risk pregnant woman with chronic hypertension with no increase in soluble fms-like tyrosine kinase-1 concentrations. | J698: Asli | K698: Terverifikasi
A699: 695 | B699: S1199 | C699: PubMed | D699: 10.1164/rccm.201605-1081cp | E699: Brochard L, Slutsky A, Pesenti A | F699: Mechanical Ventilation to Minimize Progression of Lung Injury in Acute Respiratory Failure | G699: 2017 | H699: American Journal of Respiratory and Critical Care Medicine | I699: Mechanical ventilation is used to sustain life in patients with acute respiratory failure. A major concern in mechanically ventilated patients is the risk of ventilator-induced lung injury, which is partially prevented by lung-protective ventilation. Spontaneously breathing, nonintubated patients with acute respiratory failure may have a high respiratory drive and breathe with large tidal volumes and potentially injurious transpulmonary pressure swings. In patients with existing lung injury, regional forces generated by the respiratory muscles may lead to injurious effects on a regional level. In addition, the increase in transmural pulmonary vascular pressure swings caused by inspiratory effort may worsen vascular leakage. Recent data suggest that these patients may develop lung injury that is similar to the ventilator-induced lung injury observed in mechanically ventilated patients. As such, we argue that application of a lung-protective ventilation, today best applied with sedation and endotracheal intubation, might be considered a prophylactic therapy, rather than just a supportive therapy, to minimize the progression of lung injury from a form of patient self-inflicted lung injury. This has important implications for the management of these patients. | J699: Asli | K699: Terverifikasi
A700: 696 | B700: S0845 | C700: PubMed | D700: 10.3389/fmed.2026.1773798 | E700: Dueñas-Castell C, Correa-Guerrero J, Rodelo-Barrios D, Osorio-Rodríguez E, Aguilar-Schotborgh M, Almanza-Hurtado A, Borré-Naranjo D, Ortiz-Ruiz G | F700: PaCO2: a treatable trait in acute respiratory failure | G700: 2026 | H700: Frontiers in Medicine | I700: Treatable traits are a cornerstone of personalized (precision) medicine. Arterial carbon dioxide tension (PaCO 2 ) is a fundamental measure in acute respiratory failure. We aimed to determine whether PaCO 2 can be considered a treatable trait in patients with acute respiratory failure. We performed an electronic search to identify studies addressing hypercapnia and hypocapnia as clinically actionable features in respiratory insufficiency, including their prognostic value and role as potential treatment targets. A systematic snowball approach (backward and forward citation tracking) was applied to capture additional relevant articles. Evidence was synthesized narratively to contextualize findings within the conceptual framework of PaCO 2 as a treatable trait. PaCO 2 supports classification of acute respiratory failure as hypercapnic or non-hypercapnic, informs prognosis, and helps define non-invasive management with high-flow nasal cannula or non-invasive ventilation. In intubated patients, PaCO 2 contributes to monitoring ventilatory strategies such as lung-protective ventilation and prone positioning, and it helps interpret outcome-relevant variables such as ventilatory ratio and mechanical power. Across the peri-extubation period, PaCO 2 is associated with clinically meaningful outcomes before, during, and after ventilator weaning and can guide selection of post-extubation non-invasive support to reduce reintubation risk. PaCO 2 may be considered a treatable trait across the pre-intubation, invasively ventilated, and post-extubation phases of acute respiratory failure. Further research is needed to define clinically actionable limits and targets in relevant patient subgroups, including safety margins in relation to pH and exposure time. | J700: Asli | K700: Terverifikasi
A701: 697 | B701: S0644 | C701: PubMed | D701: 10.1016/s1388-9842(00)00061-1 | E701: Cohen-Solal A, Bouhour JB, Thebaut JF | F701: The Management of Patients with Heart Failure in France | G701: 2000 | H701: European Journal of Heart Failure | I701: Heart failure is becoming, in France as in other countries, a major public health problem, occurring in elderly patients with concurrent disease. A general overview of the current care of heart failure patients in France is provided in this article, and some ideas about possible ways of improving the present management of heart failure. | J701: Asli | K701: Terverifikasi
A702: 698 | B702: S1110 | C702: PubMed | D702: 10.1136/heart.83.2.147 | E702: Davies LC, Francis DP, Piepoli M, Scott AC, Ponikowski P, Coats AJS | F702: Chronic heart failure in the elderly: value of cardiopulmonary exercise testing in risk stratification | G702: 2000 | H702: Heart | I702: To assess the value of cardiopulmonary exercise testing in predicting prognosis in a cohort of elderly patients with chronic heart failure (CHF). A retrospective cohort study of all patients with CHF over the age of 70 years assessed between January 1992 and May 1997. Tertiary centre. 50 patients (mean (SD) age 75.9 (4.5) years, 8 women) with CHF New York Heart Association (NYHA) class I (3 patients), II (25 patients), III (20 patients), and IV (2 patients). Follow up was complete for two years in all patients. The patients underwent cardiopulmonary exercise testing (peak oxygen consumption 15.2 (4.5) ml/kg/min, minute ventilation/carbon dioxide production (VE/V co 2 ) slope 38.7 (11.8)); radionucleide ventriculography (left ventricular ejection fraction 32.8 (14.3)%); serum sodium measurement (139 (2.8) mmol/l); and echocardiography (left ventricular end diastolic dimension 6.1 (1.1) cm, left ventricular end systolic dimension 4.7 (1.5) cm). At the end of follow up in May 1999, 26 patients had died. The median follow up of the survivors was 47.7 months (interquartile range 31.5–53.5 months). On univariate analysis VE/V co 2 slope (p &lt; 0.0001), NYHA class (p &lt; 0.001), peak oxygen uptake (V o 2 ) (p &lt; 0.01), left ventricular end systolic dimension (p &lt; 0.05), and serum sodium concentration (p &lt; 0.05) had significant predictive power. Stepwise multivariate analysis identified only VE/V co 2 slope (p &lt; 0.01), NYHA class (p &lt; 0.05), and peak V o 2 (p&lt; 0.05) as conveying significant independent prognostic information. Elderly patients with CHF have a high mortality, with the majority dead within two years. Cardiopulmonary exercise testing provides important information for risk stratification within this group and its use should not be neglected. | J702: Asli | K702: Terverifikasi
... A966: 962 | B966: S1861 | C966: PubMed | D966: 10.1186/s13256-021-02704-w | E966: Takahashi K, Nishijima K, Yamaguchi M, Matsumoto K, Sugai S, Enomoto T | F966: Noninvasive positive-pressure ventilation in pregnancy to treat acute pulmonary edema induced by tocolytic agents: a case report | G966: 2021 | H966: Journal of Medical Case Reports | I966: We report a case of pulmonary edema induced by tocolytic agents that was successfully managed with noninvasive positive-pressure ventilation (NPPV) and resulted in extended gestation. A 36-year-old Japanese pregnant woman received tocolytic therapy with ritodrine hydrochloride, magnesium sulfate, nifedipine, and betamethasone from 28 weeks of gestation. She developed respiratory failure. and her chest X-ray showed enlarged pulmonary vascular shadows. At 29 weeks and 1 day of gestation, she was diagnosed with pulmonary edema induced by tocolytic agents. Because respiratory failure worsened 2 days after ritodrine hydrochloride and magnesium sulfate were stopped, NPPV was initiated. Her respiratory status improved and she was weaned off of NPPV after 3 days. She underwent cesarean section because of breech presentation at 30 weeks and 0 days of gestation due to initiation of labor pains. NPPV can be safely administered in cases of tocolytic agent-induced pulmonary edema during pregnancy. | J966: Asli | K966: Terverifikasi
A967: 963 | B967: S1941 | C967: PubMed | D967: 10.1101/2023.02.20.23286207 | E967: Ogbu I, Hakobyan B, Sossou C, Levisman J, Obiagwu C, Danielian A | F967: The Snoring Survivors | G967: 2023 | I967: The routine administration of supplemental oxygen to non-hypoxic patients with acute myocardial infarction has been abandoned for lack of mortality benefit. However, the benefits of continuous positive airway pressure (CPAP) use in patients hospitalized with acute cardiovascular disease and concomitant obstructive sleep apnea (OSA) remain to be elucidated. Using ICD-10-CM codes, we searched the 2016-2019 Nationwide Inpatient Sample for patients diagnosed with unstable angina, acute myocardial infarction (AMI), acute decompensated heart failure (ADHF), and atrial fibrillation with rapid ventricular response (AFRVR), who also carried a diagnosis of OSA. We identified in-hospital CPAP use with ICD-10-PCS codes. In-hospital death, length of stay (LOS) and hospital charges were compared between patients with and without OSA, and between OSA patients with and without CPAP use. Our sample included 2,959,991 patients, of which 1.5% were diagnosed with UA, 30.3% with AMI, 37.5% with ADHF, and 45.8% with AF. OSA was present in 12.3%. Patients with OSA were more likely to be younger, male, smokers, obese, have chronic obstructive pulmonary disease, renal failure, and heart failure ( p &lt; 0.001 for all). Patients with OSA had significantly lower in-hospital mortality (aOR: 0.71, 95% CI [0.7-0.73]). Among patients with OSA, CPAP use significantly increased the odds of in-hospital death (aOR: 1.51, 95% CI [1.44-1.60]), LOS (adjusted mean difference of 1.49 days, 95% CI [1.43, 1.55]), and hospital charges (adjusted mean difference of $1168, 95% CI [273, 2062]). Our study showed that patients with recognized OSA and hospitalized for AMI, ADHF or AFRVR, who were not treated with CPAP, had significantly lower in-hospital mortality and resource utilization. | J967: Asli | K967: Terverifikasi
A968: 964 | B968: S1765 | C968: PubMed | D968: 10.1177/0310057x0002800114 | E968: McConkey PP | F968: Postobstructive Pulmonary Oedema—A Case Series and Review | G968: 2000 | H968: Anaesthesia and Intensive Care | I968: Six cases of post-extubation pulmonary oedema in otherwise healthy patients are reported. All were preceded by an episode of laryngospasm and followed a clinical course similar to that previously documented in cases of post-obstructive pulmonary oedema. Frank haemoptysis was a feature of five of the presentations. One patient was reintubated and ventilated, two were admitted to the intensive care unit for mask CPAP, one was managed with CPAP in the recovery ward and two with supplemental oxygen only. All cases resolved fully within 24 hours. Some evidence points to the syndrome being the result of airway bleeding rather than true pulmonary oedema. The literature suggests that it occurs more commonly than is generally thought, with a frequency of 0.05 to 0.1% of all anaesthetics, and is often unrecognised or misdiagnosed. Most cases occur in the early postoperative period, so anaesthetists are well placed to witness, investigate and manage this interesting condition. | J968: Asli | K968: Terverifikasi
A969: 965 | B969: S1296 | C969: PubMed | D969: 10.1016/s1388-9842(00)00078-7 | E969: Genth-Zotz S, Zotz RJ, Sigmund M, Hanrath P, Hartmann D, Böhm M, Waagstein F, Treese N, Meyer J, Darius H | F969: MIC Trial: Metoprolol in Patients with Mild to Moderate Heart Failure: Effects on Ventricular Function and Cardiopulmonary Exercise Testing | G969: 2000 | H969: European Journal of Heart Failure | I969: Beta-blocker therapy results in a functional benefit in patients with heart failure (CHF) due to idiopathic dilated cardiomyopathy (DCM). This study assessed if similar effects were observed in patients with ischemic heart disease (CAD), NYHA II–III after 6 months of therapy with metoprolol. Fifty-two patients with CHF secondary to DCM (26 patients) and CAD (26 patients) and a left ventricular ejection fraction (EF) &amp;lt; 40% were enrolled in the placebo-controlled study. The study medication was titrated over 6 weeks, the mean final dosage was 135 mg/day. Three patients died due to cardiogenic shock, two received placebo and one metoprolol. Eight patients did not complete the study due to non-compliance. Metoprolol significantly reduced heart rate at rest and after submaximal and maximal exercise. V̇o2-max and V̇o2-AT as well as the 6-min walk test improved significantly after metoprolol treatment. There was a significant increase in EF at rest (27.3–35.2%), submaximal (28.5–37.7%) and maximal exercise (28.7–40.9%) in the metoprolol-treated patients. No differences were found between patients with CAD and DCM. We also observed reduced left ventricular volumes. The additional therapy with metoprolol improved cardiac function and the cardiopulmonary exercise capacity in patients with CHF. | J969: Asli | K969: Terverifikasi
A970: 966 | B970: S1631 | C970: PubMed | D970: 10.1016/s1388-9842(01)00126-x | E970: Stoschitzky K, Koshucharova G, Zweiker R, Maier R, Watzinger N, Fruhwald FM, Klein W | F970: Differing Beta-Blocking Effects of Carvedilol and Metoprolol | G970: 2001 | H970: European Journal of Heart Failure | I970: Metoprolol is a beta1-selective beta-adrenergic antagonist while carvedilol is a non-selective beta-blocker with additional blockades of alpha1-adrenoceptors. Administration of metoprolol has been shown to cause up-regulation of beta-adrenoceptor density and to decrease nocturnal melatonin release, whereas carvedilol lacks these typical effects of beta-blocking drugs. To compare beta-blocking effects of metoprolol and carvedilol when applied orally in healthy subjects. We investigated the effects of single oral doses of clinically recommended amounts of metoprolol (50, 100 and 200 mg) and carvedilol (25, 50 and 100 mg) to those of a placebo in a randomised, double-blind, cross-over study in 12 healthy male volunteers. Two hours after oral administration of the drugs heart rate and blood pressure were measured at rest, after 10 min of exercise, and after 15 min of recovery. Metoprolol tended to decrease heart rate during exercise (−21%, −25% and −24%) to a greater extent than carvedilol (−16%, −16% and −18%). At rest, increasing doses of metoprolol caused decreasing heart rates (62, 60 and 58 beats/min) whereas increasing doses of carvedilol caused increasing heart rates (62, 66 and 69 beats/min), 50 and 100 mg carvedilol failed to differ significantly from the placebo (71 beats/min). We conclude that clinically recommended doses of carvedilol cause a clinically relevant beta-blockade in humans predominantly during exercise where it appears to be slightly (although not significantly) less effective than metoprolol. On the other hand, the effects of carvedilol on heart rate at rest appear rather weak, particularly in subjects with a low sympathetic tone. This might be caused by a reflex increase on sympathetic drive secondary to peripheral vasodilation resulting from the alpha-blocking effects of the drug. These results might be helpful in explaining why carvedilol, in contrast to metoprolol, may fail to cause up-regulation of beta-adrenoceptor density and does not decrease nocturnal melatonin release. This, in turn, may be a reason for the weak side-effects of carvedilol resulting from the beta-blockade. In addition, our data might be of interest in the interpretation of the forthcoming results of the COMET trial, although it has to be emphasised that they were derived from healthy subjects and, therefore, cannot be directly extrapolated to patients with heart failure. | J970: Asli | K970: Terverifikasi
A971: 967 | B971: S1185 | C971: PubMed | D971: 10.1056/nejmoa2211680 | E971: Lee DS, Straus SE, Farkouh ME, Austin PC, Taljaard M, Chong A, Fahim C, Poon S, Cram P, Smith S, McKelvie RS, Porepa L, Hartleib M, Mitoff P, Iwanochko RM, MacDougall A, Shadowitz S, Abrams H, Elbarasi E, Fang J, Udell JA, Schull MJ, Mak S, Ross HJ | F971: Trial of an Intervention to Improve Acute Heart Failure Outcomes | G971: 2023 | H971: New England Journal of Medicine | I971: Acute heart failure is a serious condition commonly seen in the emergency department (ED). The HEARTRISK6 Scale has been recently developed to identify the risk of poor outcomes but has not been tested. We sought to describe the management and outcomes of ED patients with acute heart failure and to evaluate the potential impact of the HEARTRISK6 Scale. We conducted a health records review of 300 consecutive acute heart failure patients presenting to two tertiary care EDs. Two evaluators abstracted clinical variables, ED management and treatment details, and patient outcomes using the electronic health records platform (EPIC) and attending physicians verified the data. The primary outcome measure was a short-term serious outcome, as shown in Results. In addition, the HEARTRISK6 score was calculated retrospectively. We included 300 patients with mean age of 78.5 years, 51.0% male, 56.3% arrival by ambulance, and 67.0% admitted to hospital. 25.3% experienced a short-term serious outcome 1) after admission (N = 201): non-invasive ventilation 14.9%, intubation 1.5%, major cardiac procedure 5.0%, myocardial infarction 2.0%, death 8.5%; 2) after ED discharge (N = 99): return to ED 21.2%, death 4.0%. Those initially admitted experienced a much higher proportion of serious outcomes compared to those discharged (29.9% vs. 16.2%). A HEARTRISK6 Scale cut-point score of ≥ 1 would have had a sensitivity of 91.0%, specificity 24.5%, and negative likelihood ratio 0.37 for short-term serious outcomes and suggested hospital admission for 80.7% of cases. There was a large range of severity of illness of acute heart failure patients and a wide variety of treatments were administered in the ED. Both admitted and discharged patients experienced a high proportion of poor outcomes. The HEARTRISK6 Scale showed a high sensitivity for short-term serious outcomes but with the potential to increase hospital admissions. Further validation of the HEARTRISK6 Scale is required before routine clinical use. | J971: Asli | K971: Terverifikasi
A972: 968 | B972: S2075 | C972: PubMed | D972: 10.1111/j.1365-2044.1992.tb02172.x | E972: THOMAS AN, RYAN JP, DORAN BRH, POLLARD BJ | F972: Nasal CPAP after coronary artery surgery | G972: 1992 | H972: Anaesthesia | I972: Two groups of 14 patients were compared after coronary artery bypass surgery where the left internal mammary artery had been used as a conduit. One group received nasal continuous positive airway pressure for 1 h, the other group acted as a control. Mean pulmonary shunt fraction was 16.3% before, 12.6% during and 15.7% after continuous positive airways pressure. In the control group the shunt fraction fell from 17.3% to 16.8%. The reduction in shunt fraction was significantly greater with nasal continuous positive airways pressure than in the control group (p = 0.016). There was a significant reduction (p = 0.025) in respiratory rate from 18.3 to 16.7 breath.min –1 during continuous positive airway pressure. Other measured cardiorespiratory variables did not differ significantly between the groups. Visual analogue scores showed no significant difference in chest pain or mask comfort between the groups. The ease of breathing score was, however, significantly better in the continuous positive airways pressure group, 7.5 (SD 1.8) cm and control 5.6 (SD 2.6) cm. | J972: Asli | K972: Terverifikasi
A973: 969 | B973: S0997 | C973: PubMed | D973: 10.1097/00000542-200006000-00019 | E973: Brimacombe J, Keller C, Hörmann C | F973: Pressure Support Ventilation versus Continuous Positive Airway Pressure with the Laryngeal Mask Airway | G973: 2000 | H973: Anesthesiology | I973: The authors tested the hypothesis that pressure support ventilation (PSV) provides more effective gas exchange than does unassisted ventilation with continuous positive airway pressure (CPAP) in anesthetized adult patients treated using the laryngeal mask airway. Forty patients were randomized to two equal-sized crossover groups, and data were collected before surgery. In group 1, patients underwent CPAP, PSV, and CPAP in sequence. In group 2, patients underwent PSV, CPAP, and PSV in sequence. PSV comprised positive end expiratory pressure set at 5 cm H2O and inspiratory pressure support set at 5 cm H2O above positive end expiratory pressure. CPAP was set at 5 cm H2O. Each ventilatory mode was maintained for 10 min. The following data were recorded every minute for the last 5 min of each ventilatory mode and the average reading taken: end tidal carbon dioxide, oxygen saturation, expired tidal volume, leak fraction, respiratory rate, noninvasive mean arterial pressure, and heart rate. In both groups, PSV showed lower end tidal carbon dioxide (P &lt; 0.001), higher oxygen saturation, (P &lt; 0.001), and higher expired tidal volume (P &lt; 0.001) compared with CPAP. In both groups, PSV had similar leak fraction, respiratory rate, mean arterial pressure, and heart rate compared with CPAP. In group 1, measurements for CPAP were similar before and after PSV. In group 2, measurements for PSV were similar before and after CPAP. The authors concluded that PSV provides more effective gas exchange than does unassisted ventilation with CPAP during LMA anesthesia while preserving leak fraction and hemodynamic homeostasis. | J973: Asli | K973: Terverifikasi
A974: 970 | B974: S0624 | C974: PubMed | D974: 10.1183/09031936.96.09061240 | E974: Barbe F, Togores B, Rubi M, Pons S, Maimo A, Agusti A | F974: Noninvasive ventilatory support does not facilitate recovery from acute respiratory failure in chronic obstructive pulmonary disease | G974: 1996 | H974: European Respiratory Journal | I974: This investigation evaluates, in a prospective, randomized and controlled manner, whether noninvasive ventilatory support (NIVS) with bilevel positive airway pressure (BiPAP) facilitates recovery from acute respiratory failure (ARF) in patients with chronic obstructive pulmonary disease (COPD). Twenty four patients (mean age (+/-SEM) 68 +/- 2 yrs) with COPD (forced expiratory volume in one second (FEV1) at discharge 33 +/- 2% predicted), who attended the emergency room because of ARF (pH 7.33 +/- 0.01; arterial oxygen tension (Pa,O2) 6.0 +/- 0.2 kPa; arterial carbon dioxide tension (Pa,CO2) 7.9 +/- 0.3 kPa), were initially randomized. Four out of the 14 patients (29%) allocated to received NIVS did not tolerate it. Of the remaining 20 patients, 10 received NIVS with BiPAP in a conventional hospital ward during the first 3 days of hospitalization (two daytime sessions of 3 h duration each). All 20 subjects were treated with oxygen, bronchodilators and steroids. On the first and third hospitalization days, before and 30 min after withdrawing oxygen therapy and/or BiPAP ventilatory support, we measured peak expiratory flow, arterial blood gas values, ventilatory pattern, occlusion pressure (P0.1), and maximal inspiratory (MIP) and maximal expiratory (MEP) pressures. All patients were discharged without requiring tracheal intubation and mechanical ventilation. Hospitalization time was similar in both groups (11.3 +/- 1.3 vs 10.6 +/- 0.9 days, control vs BiPAP, respectively). Arterial oxygenation, respiratory acidosis and airflow obstruction improved significantly throughout hospitalization in both groups. By contrast, the ventilatory pattern, P0.1, MIP and MEP did not change. NIVS with BiPAP did not cause any significant difference between groups. We conclude that noninvasive ventilatory support with bilevel positive airway pressure does not facilitate recovery from acute respiratory failure in patients with chronic obstructive pulmonary disease. Furthermore, a substantial proportion of patients (29%) do not tolerate noninvasive ventilatory support under these circumstances. From these results, we cannot recommend the use of noninvasive ventilatory support with bilevel positive airway pressure in the routine management of chronic obstructive pulmonary disease patients recovering from acute respiratory failure. | J974: Asli | K974: Terverifikasi
A975: 971 | B975: S1951 | C975: PubMed | D975: 10.1378/chest.120.5.1675 | E975: Yan AT, Bradley TD, Liu PP | F975: The Role of Continuous Positive Airway Pressure in the Treatment of Congestive Heart Failure | G975: 2001 | H975: Chest | I975: Congestive heart failure (CHF) is a serious medical condition frequently associated with sleep-related breathing disorders, which remain underdiagnosed and undertreated. Recent studies have provided important insight into the pathophysiology of sleep apnea syndrome in patients with CHF, with potential therapeutic implications. In addition to abolition of sleep apnea, continuous positive airway pressure (CPAP) treatment can improve cardiac function and relieve symptoms of CHF. Postulated mechanisms include beneficial hemodynamic effects on ventricular remodeling, unloading of fatigued respiratory muscles, and neurohormonal modulation. Although medium-term studies using CPAP to treat sleep-related breathing disorders associated with CHF have been encouraging, more definitive data from ongoing large clinical trials are necessary to clarify its therapeutic role. | J975: Asli | K975: Terverifikasi
A976: 972 | B976: S0984 | C976: PubMed | D976: 10.1046/j.1365-2265.2001.01218.x | E976: Colao A, Marzullo P, Di Somma C, Lombardi G | F976: Growth hormone and the heart | G976: 2001 | H976: Clinical Endocrinology | I976: Impaired cardiovascular function has recently been demonstrated to potentially reduce life expectancy both in GH deficiency and excess. Experimental and clinical studies have supported the evidence that GH and IGF‐I are implicated in cardiac development. In most patients with acromegaly a specific cardiomyopathy, characterized by myocardial hypertrophy with interstitial fibrosis, lympho‐mononuclear infiltration and areas of monocyte necrosis, results in biventricular concentric hypertrophy. In contrast, patients with childhood or adulthood‐onset GH deficiency (GHD) may suffer both from structural cardiac abnormalities, such as narrowing of cardiac walls, and functional impairment, that combine to reduce diastolic filling and impair left ventricular response to peak exercise. In addition, GHD patients may have an increase in vascular intima‐media thickness and a higher occurrence of atheromatous plaques, that can further aggravate the haemodynamic conditions and contribute to increased cardiovascular and cerebrovascular risk. However, several lines of evidence have suggested that the cardiovascular abnormalities can be partially reversed by suppressing GH and IGF‐I levels in acromegaly or after GH replacement therapy in GHD patients. Recently, much attention has been focussed on the ability of GH to increase cardiac mass suggesting its possible use in the treatment of chronic nonendocrine heart failure. In fact, GH administration can induce an improvement in haemodynamic and clinical status in some patients. Although these data need to be confirmed in more extensive studies, such promising results seem to open new perspectives for GH treatment in humans. | J976: Asli | K976: Terverifikasi
A977: 973 | B977: S1993 | C977: PubMed | D977: 10.1007/s13670-019-00287-5 | E977: Pulliam KE, Pritts TA | F977: Non-invasive Ventilatory Support in the Elderly | G977: 2019 | H977: Current Geriatrics Reports | I977: The first description of non-invasive ventilation use began in the 1920s. Since then, its role in patient care has evolved through increased clinical knowledge and scientific advancements. The utilization of non-invasive ventilation has broadened from initial application in acute in-hospital ICU settings to now include the outpatient settings. This review discusses the history of non-invasive ventilation and its role in acute in-hospital chronic obstructive pulmonary disease (COPD) exacerbations, cardiogenic pulmonary edema, and weaning from mechanical ventilation in the elderly. The elderly population represents a significant portion of patients hospitalized for the aforementioned conditions. These groups often have more limitations related to the use of invasive mechanical ventilation (IMV), therefore, it is essential to understand the impact of non-invasive ventilation on hospital outcomes. There is strong clinical evidence supporting the use of non-invasive ventilation in patients with respiratory failure secondary to acute COPD exacerbations and cardiogenic pulmonary edema. When compared to standard medical management of these conditions, there is a consistent and significant reduction in the rate of endotracheal intubation and in-hospital mortality. The basis of noninvasive ventilation applicability has been determined by significant reduction in mortality and intubation rates. Although survival benefits have been observed, there still remain limitations to the clinical applicability of non-invasive ventilation in certain patient populations and conditions that require further investigation. | J977: Asli | K977: Terverifikasi
A978: 974 | B978: S1083 | C978: PubMed | D978: 10.1159/000048952 | E978: Gianrossi R, Myers J, Wagner D, Dziekan G, Bloch R, Angern W, Erne P, Dubach P | F978: Effect of Beta-Blockade on Postexercise Oxygen Uptake Kinetics in Patients with Chronic Heart Failure | G978: 2001 | H978: Heart Drug | I978: &lt;i&gt;Background:&lt;/i&gt; Beta-blocking agents have recently been demonstrated to improve survival in chronic heart failure (CHF), but a debate exists regarding the influence of beta-blockade on exercise capacity in these patients. The time delay for oxygen uptake to return to baseline after exercise (VO&lt;sub&gt;2&lt;/sub&gt; recovery kinetics) has been shown to be related to the severity of CHF, skeletal muscle metabolic abnormalities and prognosis. We performed the present study to determine the effect of beta-blockade on VO&lt;sub&gt;2&lt;/sub&gt; recovery kinetics in patients with CHF. &lt;i&gt;Methods:&lt;/i&gt; Twenty-five patients with CHF were randomized to 6 months of bisoprolol (n = 10, ejection fraction = 27 ± 6%) or placebo (n = 15, ejection fraction = 25 ± 5%) therapy. Bisoprolol dosage was titrated in accordance with the Cardiac Insufficiency Bisoprolol Study protocol. Before and after the study period, oxygen uptake kinetics in recovery from maximal exercise were calculated and expressed as the slope of a single exponential relation between oxygen uptake and time during the first 3 min of recovery. &lt;i&gt;Results:&lt;/i&gt; Resting and maximal heart rates were reduced after bisoprolol therapy, by 17 (p &lt; 0.05) and 14 (p = 0.08) beats/min, respectively. Maximal oxygen uptake was unchanged in the bisoprolol (19.0 ± 4.9 vs. 19.9 ± 4.3 ml/kg/min) and placebo (18.9 ± 3.6 vs. 19.4 ± 3.6 ml/kg/min) groups. The time constants in recovery were reduced by modest and insignificant amounts in both groups (127.2 ± 41 vs. 112.6 ± 27 s for bisoprolol and 119.5 ± 55 vs. 97.3 ± 31 s for placebo). The time constant in recovery was poorly related to peak VO&lt;sub&gt;2&lt;/sub&gt; (r = –0.10). &lt;i&gt;Conclusion:&lt;/i&gt; In patients with CHF, beta-blockade does not influence exercise capacity or oxygen uptake recovery kinetics. While this study confirms the suppression of sympathetic drive which has been shown to have beneficial effects in CHF, these results suggest that beta-blockade has minimal effects on indices of exercise tolerance, including VO&lt;sub&gt;2 &lt;/sub&gt;recovery time. | J978: Asli | K978: Terverifikasi
A979: 975 | B979: S0444 | C979: PubMed | D979: 10.1136/heart.84.6.615 | E979: Krum H, Ninio D, MacDonald P | F979: Baseline predictors of tolerability to carvedilol in patients with chronic heart failure | G979: 2000 | H979: Heart | I979: To determine baseline predictors of tolerance to the α/β blocker carvedilol in everyday clinical practice. Retrospective analysis of tolerance to carvedilol in patients with chronic heart failure. Tolerance was defined as currently on carvedilol or on it at the time of death or heart transplantation. To meet the criteria for tolerance, carvedilol had to be prescribed at a stable dose for ⩾ 3 months. Everyday clinical practice, comprising both hospital specialist practice and private practice. Tolerance was assessed in all patients prescribed carvedilol for chronic heart failure in those practices. 808 consecutive patients in both hospital specialist (611 patients) and private practice (197 patients). Baseline predictors of tolerance assessed by proportional hazards analysis. Both univariate and multivariate analyses were performed. Within the entire cohort of 808 patients, 95 had stopped carvedilol, 606 were currently receiving the drug, 50 had died, and 44 had received a heart transplant. Overall, 88% of patients tolerated carvedilol (87% in the hospital specialist group, 92% in the private practitioner group). Factors that indicated impaired tolerance by univariate analysis were increased age in years (hazard ratio 1.01, 95% confidence interval (CI) 1.0 to 1.3), low diastolic blood pressure (hazard ratio 1.04, 95% CI 1.02 to 1.08), and raised plasma urea concentration (hazard ratio 1.04, 95% CI 1.02 to 1.05). New York Heart Association (NYHA) class was also a marker of tolerance (proportion not tolerated: 3% class I; 9% class II; 13% class III, 22% class IV). By multivariate analysis, no single baseline variable was an independent marker of inability to tolerate carvedilol. Tolerance was also assessed in relation to traditional precautions or relative contraindications to β blockade. Tolerance in these subgroups was: chronic obstructive airways disease/asthma 85% (89 patients), diabetes 86% (127 patients), peripheral vascular disease 84% (58 patients), concomitant amiodarone treatment 83% (230 patients), and heart rate &lt; 70 beats/min 84% (184 patients). β Blocker treatment was well tolerated in everyday clinical practice, including non-hospital-based private practice. There was no single predictor of poor tolerance on multivariate analysis, although there was a clear association with NYHA class as well as age, diastolic blood pressure, and plasma urea on univariate analysis. Carvedilol was tolerated well among selected patients with traditional contraindications to β blockade in this situation. | J979: Asli | K979: Terverifikasi
... A1259: 1255 | B1259: S0443 | C1259: PubMed | D1259: 10.1002/ejhf.1369 | E1259: Mullens W, Damman K, Harjola VP, Mebazaa A, Brunner-La Rocca HP, Martens P, Testani JM, Tang WHW, Orso F, Rossignol P, Metra M, Filippatos G, Seferovic PM, Ruschitzka F, Coats AJ | F1259: The Use of Diuretics in Heart Failure with Congestion — A Position Statement from the Heart Failure Association of the European Society of Cardiology | G1259: 2019 | H1259: European Journal of Heart Failure | I1259: The vast majority of acute heart failure episodes are characterized by increasing symptoms and signs of congestion with volume overload. The goal of therapy in those patients is the relief of congestion through achieving a state of euvolaemia, mainly through the use of diuretic therapy. The appropriate use of diuretics however remains challenging, especially when worsening renal function, diuretic resistance and electrolyte disturbances occur. This position paper focuses on the use of diuretics in heart failure with congestion. The manuscript addresses frequently encountered challenges, such as (i) evaluation of congestion and clinical euvolaemia, (ii) assessment of diuretic response/resistance in the treatment of acute heart failure, (iii) an approach towards stepped pharmacologic diuretic strategies, based upon diuretic response, and (iv) management of common electrolyte disturbances. Recommendations are made in line with available guidelines, evidence and expert opinion. | J1259: Asli | K1259: Terverifikasi
...

Sheet Skrining judul abstrak
A1: Skrining judul dan abstrak (n = 2.477)
A2: Setelah 2.262 duplikat dihapus. Rekaman dengan keputusan Lanjut ke teks lengkap dicari naskah lengkapnya.
A4: ID rekaman | B4: DOI | C4: Penulis | D4: Tahun | E4: Judul | F4: Jurnal | G4: Abstrak | H4: Desain | I4: P | J4: I | K4: C | L4: O | M4: Keputusan | N4: Alasan eksklusi
A5: S0001 | B5: 10.1152/jappl.1989.66.5.2223 | C5: Skaburskis M, Michel RP, Gatensby A, Zidulka A | D5: 1989 | E5: Effect of negative-pressure ventilation on lung water in permeability pulmonary edema | F5: Journal of Applied Physiology | G5: We have previously shown (Am. Rev. Respir. Dis. 136: 886–891, 1987) improved cardiac output in dogs with pulmonary edema ventilated with external continuous negative chest pressure ventilation (CNPV) using negative end-expiratory pressure (NEEP), compared with continuous positive-pressure ventilation (CPPV) using equivalent positive end-expiratory pressure (PEEP). The present study examined the effect on lung water of CNPV compared with CPPV to determine whether the increased venous return created by NEEP worsened pulmonary edema in dogs with acute lung injury. Oleic acid (0.06 ml/kg) was administered to 27 anesthetized dogs. Supine animals were then divided into three groups and ventilated for 6 h. The first group (n = 10) was treated with intermittent positive-pressure ventilation (IPPV) alone; the second (n = 9) received CNPV with 10 cmH2O NEEP; the third (n = 8) received CPPV with 10 cmH2O PEEP. CNPV and CPPV produced similar improvements in oxygenation over IPPV. However, cardiac output was significantly depressed by CPPV, but not by CNPV, when compared with IPPV. Although there were no differences in extravascular lung water (Qwl/dQl) between CNPV and CPPV, both significantly increased Qwl/dQl compared with IPPV (7.81 +/- 0.21 and 7.87 +/- 0.31 vs. 6.71 +/- 0.25, respectively, P less than 0.01 in both instances). CNPV and CPPV, but not IPPV, enhanced lung water accumulation in the perihilar areas where interstitial pressures may be most negative at higher lung volumes. | H5: Observasional atau lainnya | I5: Sesuai | J5: Tidak | K5: Tidak | L5: Tidak | M5: Dieksklusi | N5: Bukan intervensi NIV, CPAP, atau BiPAP
A6: S0002 | B6: 10.5005/jp-journals-10071-24400 | C6: Jindal A, Pratyusha K | D6: 2023 | E6: Non-invasive Ventilation Failure – Predict and Protect | F6: Indian Journal of Critical Care Medicine | G6: Modified heart rate, acidosis, consciousness, oxygenation and respiratory rate (HACOR) score takes into consideration pneumonia, cardiogenic pulmonary edema, pulmonary acute respiratory distress syndrome (ARDS), immunosuppression, septic shock, and the sequential organ failure assessment (SOFA) score prior to non-invasive mechanical ventilation (NIV) that would impact the success of NIV and are commonly seen in patients presenting to the emergency. Propensity score matching could have been done for similar distribution of baseline characteristics. Specific objective criteria are needed to define respiratory failure requiring intubation. How to cite this article Pratyusha K, Jindal A. Non-invasive Ventilation Failure - Predict and Protect. Indian J Crit Care Med 2023;27(2):149. | H6: Observasional atau lainnya | I6: Sesuai | J6: Sesuai | K6: Tidak | L6: Tidak | M6: Dieksklusi | N6: Desain bukan tinjauan sistematik atau uji acak
A7: S0003 | B7: 10.4103/1817-1737.146855 | C7: AlYami M, AlAhmari M, Alotaibi H, AlRabeeah S, AlBalawi I, Mubasher M | D7: 2015 | E7: Evaluation of efficacy of non-invasive ventilation in Non-COPD and non-trauma patients with acute hypoxemic respiratory failure: A systematic review and meta-analysis | F7: Annals of Thoracic Medicine | G7: Non-invasive ventilation (NIV) has been widely supported in the past two decades as an effective application in avoiding the need for endotracheal intubation (ETI) and reducing associated mortality in acute hypoxemic respiratory failure (AHRF) patients. However, the efficacy of NIV in AHRF patients, non-related to chronic obstructive pulmonary disease (COPD) and trauma is still controversial in the field of medical research. This retrospective study aimed to evaluate the efficacy of NIV as an adjunctive therapy in non-COPD and non-traumatic AHRF patients. Data of 11 randomized control trials (RCTs), which were conducted between 1990 and 2010 to determine the efficacy of NIV in non-COPD and non-traumatic AHRF patients, were reviewed from the PUBMED, MEDLINE, Cochrane Library, and EMBASE databases. Parameters monitored in this study included the ETI rate, fatal complications, mortality rate of patients, and their ICU and hospital duration of stay. Overall results showed a statistically significant decrease in the rate of ETI, mortality, and fatal complications along with reduced ICU and hospital length of stay in non-COPD and non-trauma AHRF patients of various etiologies. This systematic review suggests that non-COPD and non-trauma AHRF patients can potentially benefit from NIV as compared with conventional treatment methods. Observations from various cohort studies, observational studies, and previously published literature advocate on the efficacy of NIV for treating non-COPD and non-traumatic AHRF patients. However, considering the diversity of studied populations, further studies and more specific trials on less heterogeneous AHRF patient groups are needed to focus on this aspect. | H7: Tinjauan sistematik atau meta-analisis | I7: Tidak | J7: Sesuai | K7: Tidak | L7: Sesuai | M7: Dieksklusi | N7: Bukan populasi edema paru kardiogenik akut
A8: S0004 | B8: 10.1016/s1388-9842(00)00145-8 | C8: Thackray SDR, Witte KKA, Khand A, Dunn A, Clark AL, Cleland JGF | D8: 2001 | E8: Clinical Trials Update: Highlights of the Scientific Sessions of the American Heart Association Year 2000: Val HeFT, COPERNICUS, MERIT, CIBIS-II, BEST, AMIOVIRT, V-MAC, BREATHE, HEAT, MIRACL, FLORIDA, VIVA and the First Human Cardiac Skeletal Muscle Myoblast Transfer for Heart Failure | F8: European Journal of Heart Failure | G8: This article continues a series of reports summarising recent research developments pertinent to the topic of heart failure. This is a summary of presentations made at scientific sessions of the American Heart Association in November 2000. Clinical studies of particular interest to people caring for patients with heart failure include Val-HeFT, AMIOVIRT and V-MAC. New data from β-blockers trials are reviewed, highlights from some important developments in post-infarction care, including MIRACL and FLORIDA, discussed and results of some early studies of gene therapy reported. | H8: Observasional atau lainnya | I8: Sesuai | J8: Tidak | K8: Tidak | L8: Tidak | M8: Dieksklusi | N8: Bukan intervensi NIV, CPAP, atau BiPAP
